{"গোপনভাবে":["DAU-3841","MUS-2252"],
"গোসলনান্তে":["DAU-288"],
"গোশতপিন্ডে":["BUK-2981","BUK-6946"],
"গোনাহে":["DAU-1514","DAU-1521","MUS-436"],
"গোছাদ্বয়":["DAU-2217"],
"গোনাহর":["BUK-3691"],
"গোশতহীন":["BUK-616"],
"গোসসার":["MUS-3497"],
"গোশতখন্ড":["MUS-4843"],
"গোশতপিণ্ডে":["BUK-312"],
"গোচরে":["DAU-4399","MAJ-2019"],
"গোপনীয়তা":["BUK-3268","MAJ-1921"],
"গোবরযুক্ত":["NAS-308"],
"গোলামই":["MAJ-1960","MAJ-2529"],
"গোত্রেই":["BUK-1395","BUK-3621","MUS-6199"],
"গোন্দ":["BUK-1811"],
"গোলামেরা":["BUK-2377","DAU-2294","DAU-2869","MAJ-4136"],
"গোটার":["MUS-5878"],
"গোশত":["BUK-207","BUK-208","BUK-210","BUK-641","BUK-891","BUK-906","BUK-914","BUK-931","BUK-1389","BUK-1406","BUK-1407","BUK-1583","BUK-1601","BUK-1608","BUK-1609","BUK-1610","BUK-1611","BUK-1612","BUK-1704","BUK-1705","BUK-1707","BUK-1867","BUK-2294","BUK-2315","BUK-2323","BUK-2342","BUK-2396","BUK-2400","BUK-2407","BUK-2408","BUK-2409","BUK-2440","BUK-2442","BUK-2657","BUK-2713","BUK-2748","BUK-2772","BUK-2783","BUK-2831","BUK-2871","BUK-2912","BUK-2934","BUK-3018","BUK-3019","BUK-3026","BUK-3095","BUK-3123","BUK-3126","BUK-3160","BUK-3207","BUK-3233","BUK-3352","BUK-3354","BUK-3498","BUK-3544","BUK-3565","BUK-3573","BUK-3707","BUK-3801","BUK-3802","BUK-3840","BUK-3864","BUK-3882","BUK-3884","BUK-3898","BUK-3900","BUK-3901","BUK-3902","BUK-3903","BUK-3904","BUK-3905","BUK-3906","BUK-3907","BUK-3909","BUK-3910","BUK-4043","BUK-4153","BUK-4353","BUK-4391","BUK-4396","BUK-4397","BUK-4431","BUK-4714","BUK-4726","BUK-4742","BUK-4782","BUK-4899","BUK-5012","BUK-5029","BUK-5036","BUK-5101","BUK-5111","BUK-5121","BUK-5123","BUK-5126","BUK-5127","BUK-5131","BUK-5162","BUK-5170","BUK-5171","BUK-5173","BUK-5174","BUK-5717","BUK-5877","BUK-5892","BUK-6142","BUK-6264","BUK-6490","BUK-6730","BUK-6771","DAU-66","DAU-67","DAU-184","DAU-189","DAU-190","DAU-191","DAU-193","DAU-948","DAU-1655","DAU-1715","DAU-1716","DAU-1763","DAU-1765","DAU-1797","DAU-1849","DAU-1850","DAU-1851","DAU-1903","DAU-2055","DAU-2408","DAU-2540","DAU-2641","DAU-2653","DAU-2791","DAU-2792","DAU-2803","DAU-2804","DAU-2807","DAU-2811","DAU-2814","DAU-2820","DAU-2821","DAU-2824","DAU-2849","DAU-3299","DAU-3453","DAU-3656","DAU-3677","DAU-3736","DAU-3739","DAU-3740","DAU-3743","DAU-3746","DAU-3747","DAU-3748","DAU-3755","DAU-3762","DAU-3763","DAU-3764","DAU-3765","DAU-3766","DAU-3767","DAU-3768","DAU-3773","DAU-3796","DAU-3797","DAU-3812","DAU-4074","DAU-4375","DAU-4405","DAU-4446","DAU-4447","DAU-4448","DAU-4449","DAU-4533","DAU-4801","DAU-4855","DAU-5054","DAU-5084","MAJ-488","MAJ-489","MAJ-491","MAJ-493","MAJ-494","MAJ-495","MAJ-497","MAJ-525","MAJ-594","MAJ-748","MAJ-1722","MAJ-1910","MAJ-1961","MAJ-2855","MAJ-2981","MAJ-3074","MAJ-3090","MAJ-3091","MAJ-3093","MAJ-3105","MAJ-3154","MAJ-3157","MAJ-3158","MAJ-3159","MAJ-3160","MAJ-3167","MAJ-3174","MAJ-3189","MAJ-3190","MAJ-3191","MAJ-3192","MAJ-3194","MAJ-3195","MAJ-3196","MAJ-3197","MAJ-3198","MAJ-3241","MAJ-3243","MAJ-3300","MAJ-3303","MAJ-3305","MAJ-3306","MAJ-3307","MAJ-3308","MAJ-3310","MAJ-3311","MAJ-3312","MAJ-3361","MAJ-3546","MAJ-3763","MAJ-3938","MAJ-4079","MAJ-4080","MUS-221","MUS-376","MUS-681","MUS-682","MUS-683","MUS-684","MUS-687","MUS-689","MUS-1291","MUS-1356","MUS-2241","MUS-2356","MUS-2542","MUS-2716","MUS-2717","MUS-2718","MUS-2720","MUS-2721","MUS-2723","MUS-2725","MUS-2726","MUS-2728","MUS-2731","MUS-2796","MUS-3050","MUS-3053","MUS-3086","MUS-3088","MUS-3301","MUS-3303","MUS-3305","MUS-3369","MUS-3371","MUS-3373","MUS-3519","MUS-3641","MUS-3642","MUS-3644","MUS-3949","MUS-4119","MUS-4122","MUS-4517","MUS-4567","MUS-4843","MUS-4851","MUS-4852","MUS-4853","MUS-4860","MUS-4862","MUS-4867","MUS-4875","MUS-4879","MUS-4883","MUS-4904","MUS-4911","MUS-4913","MUS-4936","MUS-4939","MUS-4941","MUS-4942","MUS-4944","MUS-4945","MUS-4951","MUS-4952","MUS-5152","MUS-5191","MUS-5699","MUS-5878","MUS-6060","MUS-6166","MUS-6482","MUS-7013","MUS-7169","NAS-69","NAS-70","NAS-165","NAS-182","NAS-183","NAS-184","NAS-266","NAS-327","NAS-342","NAS-377","NAS-380","NAS-2036","NAS-2037","NAS-2539","NAS-2616","NAS-2824","NAS-2827","NAS-2828","NAS-3368","NAS-3369","NAS-3385","NAS-3451","NAS-3454","NAS-3457","NAS-3458","NAS-3761","NAS-3949","NAS-3950","NAS-4218","NAS-4226","NAS-4230","NAS-4231","NAS-4232","NAS-4237","NAS-4298","NAS-4317","NAS-4318","NAS-4319","NAS-4328","NAS-4329","NAS-4330","NAS-4331","NAS-4332","NAS-4333","NAS-4334","NAS-4335","NAS-4336","NAS-4337","NAS-4339","NAS-4340","NAS-4341","NAS-4342","NAS-4344","NAS-4345","NAS-4348","NAS-4397","NAS-4421","NAS-4424","NAS-4426","NAS-4427","NAS-4428","NAS-4429","NAS-4430","NAS-4431","NAS-4432","NAS-4433","NAS-4434","NAS-4435","NAS-4437","NAS-4448","NAS-4643","NAS-4645","NAS-5652","TIR-66","TIR-80","TIR-81","TIR-769","TIR-813","TIR-848","TIR-849","TIR-850","TIR-1099","TIR-1122","TIR-1461","TIR-1484","TIR-1486","TIR-1514","TIR-1515","TIR-1516","TIR-1517","TIR-1800","TIR-1801","TIR-1803","TIR-1831","TIR-1833","TIR-1834","TIR-1835","TIR-1836","TIR-1839","TIR-1840","TIR-1842","TIR-1843","TIR-1844","TIR-1845","TIR-1854","TIR-2359","TIR-2437","TIR-2609","TIR-3054","TIR-3061","TIR-3117","TIR-3153","TIR-3258"],
"গোত্রে":["BUK-39","BUK-416","BUK-676","BUK-1114","BUK-1145","BUK-2132","BUK-2512","BUK-2809","BUK-2811","BUK-3520","BUK-3557","BUK-3567","BUK-3615","BUK-3625","BUK-3947","BUK-4055","BUK-4210","BUK-4222","BUK-4227","BUK-6607","BUK-6700","DAU-453","DAU-600","DAU-1068","DAU-2517","DAU-3301","DAU-3857","DAU-4853","MAJ-1032","MAJ-1165","MAJ-1876","MAJ-2677","MAJ-3055","MAJ-3074","MAJ-4053","MUS-833","MUS-835","MUS-4450","MUS-5750","MUS-6265","MUS-6946","NAS-703","NAS-1330","NAS-3891","NAS-4271","NAS-4706","TIR-1133","TIR-1610","TIR-2099","TIR-2182","TIR-2223","TIR-3086","TIR-3270","TIR-3532","TIR-3608"],
"গোত্রীয়া":["NAS-4901"],
"গোপনের":["BUK-4212"],
"গোলাটির":["BUK-3757"],
"গোত্রেকে":["DAU-4572"],
"গোচরিভূত":["MAJ-1462"],
"গোত্রদের":["BUK-2565"],
"গোলানো":["BUK-2442"],
"গোনাহের":["DAU-1504","DAU-1521","DAU-2189","MUS-125","MUS-4727","MUS-6335"],
"গোসলরত":["BUK-276","DAU-1840","MUS-2760"],
"গোলাপী":["BUK-1452","BUK-1521","BUK-3295","DAU-4023","MUS-7106"],
"গোলামরূপে":["BUK-6298"],
"গোছাওয়ালা":["MUS-6064"],
"গোঁফের":["DAU-4695"],
"গোশতগুলো":["BUK-5717"],
"গোলামীতে":["DAU-3920"],
"গোনাহগার":["BUK-6172","DAU-1692","MUS-6595"],
"গোসাপ":["NAS-4315","NAS-4316","NAS-4317","NAS-4320","NAS-4321","NAS-4322","NAS-4323"],
"গোত্রগুলির":["MUS-5749"],
"গোনাহ":["BUK-2207","BUK-3308","BUK-6090","DAU-935","DAU-936","DAU-1310","DAU-1315","DAU-1489","DAU-1517","DAU-1521","MUS-159","MUS-1652","MUS-1685","MUS-6181","MUS-6327","MUS-6328","MUS-6329","MUS-6332","MUS-6338","MUS-6355","TIR-177"],
"গোলামটিকে":["BUK-6259","MAJ-2847","MUS-1099"],
"গোলমটিকে":["BUK-6696"],
"গোছারও":["MUS-472"],
"গোপনকে":["TIR-3586"],
"গোলাকৃতি":["BUK-3109","BUK-3343","BUK-6650","BUK-6651"],
"গোত্রভুক্ত":["DAU-1686","MAJ-2612","MUS-6176","TIR-2226"],
"গোত্রই":["BUK-2485","BUK-3971","MUS-5749","NAS-637"],
"গোত্রদ্বয়ের":["BUK-3070","BUK-3506","BUK-3531","BUK-4045","MUS-1420","MUS-3045","MUS-4452","TIR-3180"],
"গোড়ালীর":["DAU-783","DAU-2565","MUS-5282","TIR-1214","TIR-1790"],
"গোঁছা":["NAS-2907"],
"গোটা":["BUK-50","BUK-3665","BUK-3882","BUK-4076","BUK-4156","DAU-317","DAU-1297","DAU-1461","DAU-1985","DAU-4216","MAJ-536","MAJ-630","MAJ-642","MAJ-1060","MAJ-1649","MAJ-1855","MAJ-2619","MAJ-2934","MAJ-3010","MAJ-3012","MAJ-3048","MAJ-3108","MAJ-3225","MAJ-3274","MAJ-3559","MAJ-3560","MAJ-3630","MAJ-3761","MAJ-3951","MAJ-4077","MAJ-4141","MAJ-4266","MUS-770","MUS-2593","MUS-2618","MUS-2648","MUS-2823","MUS-3112","MUS-4658","MUS-4714","MUS-4715","TIR-886"],
"গোবরে":["DAU-5028"],
"গোছায়":["BUK-371","BUK-3882","DAU-3854","MAJ-1459"],
"গোড়ায়":["BUK-871","BUK-1303","BUK-3110","DAU-252","DAU-255","DAU-314","DAU-316","DAU-359","DAU-1080","MAJ-642","MAJ-1053","MUS-87","MUS-611","MUS-643","MUS-3559","NAS-1507","NAS-1518","NAS-1521","TIR-2499"],
"গোস্যাসহ":["MUS-3615"],
"গোড়ালীগুলোর":["BUK-166","MUS-459"],
"গোশতসহ":["BUK-3235","NAS-4340"],
"গোলাই":["BUK-3757"],
"গোড়ালির":["BUK-164","BUK-4270","DAU-662","DAU-845","MAJ-3583","MUS-517","MUS-518","MUS-1081","MUS-5280","NAS-18","NAS-111","TIR-48","TIR-1736","TIR-1737"],
"গোষ্ঠিকে":["BUK-1285"],
"গোশতও":["BUK-7045","DAU-229","DAU-1849","DAU-4533","MUS-2726","NAS-4343"],
"গোপনেও":["MUS-1809","TIR-2350"],
"গোত্রও":["BUK-3266"],
"গোলক":["MAJ-3074","MUS-2821"],
"গোশতই":["NAS-1566"],
"গোলাকার":["BUK-1830","BUK-6555","BUK-6556","DAU-1079","DAU-1174","DAU-3625","MAJ-1133","MAJ-4161","MUS-5874","NAS-1266","NAS-1271","NAS-1531"],
"গোত্রসমূহ":["BUK-4282"],
"গোলামসমূহের":["MAJ-2186"],
"গোত্রের":["BUK-48","BUK-51","BUK-61","BUK-62","BUK-87","BUK-113","BUK-233","BUK-239","BUK-337","BUK-390","BUK-409","BUK-413","BUK-425","BUK-426","BUK-427","BUK-455","BUK-485","BUK-496","BUK-498","BUK-521","BUK-575","BUK-583","BUK-600","BUK-623","BUK-634","BUK-650","BUK-666","BUK-719","BUK-767","BUK-800","BUK-848","BUK-898","BUK-949","BUK-952","BUK-957","BUK-1114","BUK-1317","BUK-1412","BUK-1413","BUK-1425","BUK-1465","BUK-1489","BUK-1490","BUK-1616","BUK-1678","BUK-1704","BUK-1705","BUK-1732","BUK-1733","BUK-1734","BUK-1753","BUK-1766","BUK-1881","BUK-2120","BUK-2121","BUK-2132","BUK-2145","BUK-2150","BUK-2159","BUK-2172","BUK-2175","BUK-2246","BUK-2261","BUK-2262","BUK-2277","BUK-2300","BUK-2306","BUK-2324","BUK-2372","BUK-2373","BUK-2413","BUK-2425","BUK-2434","BUK-2485","BUK-2511","BUK-2546","BUK-2547","BUK-2562","BUK-2590","BUK-2619","BUK-2621","BUK-2699","BUK-2729","BUK-2736","BUK-2739","BUK-2827","BUK-2831","BUK-2848","BUK-2859","BUK-2873","BUK-2875","BUK-2876","BUK-2891","BUK-2904","BUK-2911","BUK-2912","BUK-2926","BUK-2930","BUK-3012","BUK-3107","BUK-3125","BUK-3126","BUK-3134","BUK-3138","BUK-3148","BUK-3156","BUK-3157","BUK-3195","BUK-3196","BUK-3198","BUK-3229","BUK-3244","BUK-3245","BUK-3249","BUK-3257","BUK-3260","BUK-3266","BUK-3267","BUK-3268","BUK-3270","BUK-3272","BUK-3277","BUK-3328","BUK-3340","BUK-3347","BUK-3352","BUK-3453","BUK-3464","BUK-3465","BUK-3505","BUK-3518","BUK-3535","BUK-3549","BUK-3557","BUK-3558","BUK-3567","BUK-3582","BUK-3585","BUK-3625","BUK-3637","BUK-3676","BUK-3677","BUK-3700","BUK-3701","BUK-3713","BUK-3720","BUK-3721","BUK-3724","BUK-3727","BUK-3735","BUK-3738","BUK-3740","BUK-3769","BUK-3786","BUK-3789","BUK-3791","BUK-3794","BUK-3795","BUK-3817","BUK-3818","BUK-3821","BUK-3822","BUK-3824","BUK-3831","BUK-3835","BUK-3836","BUK-3848","BUK-3868","BUK-3878","BUK-3879","BUK-3883","BUK-3884","BUK-3886","BUK-3913","BUK-3918","BUK-3923","BUK-3943","BUK-3947","BUK-3952","BUK-3971","BUK-3973","BUK-3981","BUK-3982","BUK-3983","BUK-3984","BUK-3987","BUK-3995","BUK-3997","BUK-4008","BUK-4009","BUK-4017","BUK-4018","BUK-4027","BUK-4029","BUK-4030","BUK-4031","BUK-4032","BUK-4034","BUK-4043","BUK-4057","BUK-4076","BUK-4077","BUK-4204","BUK-4227","BUK-4243","BUK-4247","BUK-4351","BUK-4386","BUK-4391","BUK-4398","BUK-4412","BUK-4453","BUK-4459","BUK-4481","BUK-4483","BUK-4497","BUK-4519","BUK-4521","BUK-4552","BUK-4555","BUK-4578","BUK-4812","BUK-4892","BUK-4958","BUK-5009","BUK-5040","BUK-5235","BUK-5306","BUK-5325","BUK-5338","BUK-5351","BUK-5354","BUK-5401","BUK-5540","BUK-5627","BUK-5701","BUK-5795","BUK-5828","BUK-5832","BUK-5949","BUK-6150","BUK-6194","BUK-6250","BUK-6264","BUK-6284","BUK-6346","BUK-6348","BUK-6400","BUK-6406","BUK-6414","BUK-6431","BUK-6432","BUK-6437","BUK-6442","BUK-6455","BUK-6471","BUK-6508","BUK-6631","BUK-6686","BUK-6699","BUK-6702","BUK-6749","BUK-6764","BUK-6770","BUK-6840","BUK-6849","BUK-6926","BUK-6939","BUK-6948","BUK-6971","BUK-7045","BUK-7046","DAU-142","DAU-229","DAU-313","DAU-453","DAU-454","DAU-487","DAU-519","DAU-531","DAU-578","DAU-585","DAU-600","DAU-774","DAU-816","DAU-926","DAU-940","DAU-941","DAU-1068","DAU-1080","DAU-1236","DAU-1241","DAU-1273","DAU-1393","DAU-1478","DAU-1581","DAU-1600","DAU-1601","DAU-1602","DAU-1627","DAU-1763","DAU-1799","DAU-1809","DAU-1810","DAU-1849","DAU-1903","DAU-1913","DAU-1914","DAU-1995","DAU-2006","DAU-2012","DAU-2112","DAU-2117","DAU-2152","DAU-2169","DAU-2193","DAU-2199","DAU-2208","DAU-2210","DAU-2230","DAU-2250","DAU-2254","DAU-2269","DAU-2279","DAU-2281","DAU-2300","DAU-2439","DAU-2467","DAU-2493","DAU-2502","DAU-2531","DAU-2567","DAU-2613","DAU-2625","DAU-2630","DAU-2637","DAU-2646","DAU-2651","DAU-2652","DAU-2669","DAU-2670","DAU-2671","DAU-2672","DAU-2684","DAU-2688","DAU-2710","DAU-2726","DAU-2741","DAU-2744","DAU-2750","DAU-2763","DAU-2771","DAU-2777","DAU-2790","DAU-2814","DAU-2893","DAU-2894","DAU-2936","DAU-2953","DAU-2954","DAU-2955","DAU-2962","DAU-2975","DAU-2988","DAU-2995","DAU-3016","DAU-3017","DAU-3040","DAU-3044","DAU-3056","DAU-3057","DAU-3059","DAU-3229","DAU-3230","DAU-3258","DAU-3279","DAU-3301","DAU-3308","DAU-3383","DAU-3539","DAU-3552","DAU-3567","DAU-3573","DAU-3583","DAU-3650","DAU-3651","DAU-3653","DAU-3654","DAU-3666","DAU-3835","DAU-3912","DAU-3995","DAU-3998","DAU-4007","DAU-4027","DAU-4038","DAU-4045","DAU-4082","DAU-4085","DAU-4107","DAU-4122","DAU-4193","DAU-4198","DAU-4237","DAU-4275","DAU-4303","DAU-4313","DAU-4322","DAU-4331","DAU-4343","DAU-4345","DAU-4347","DAU-4350","DAU-4352","DAU-4367","DAU-4372","DAU-4375","DAU-4376","DAU-4380","DAU-4385","DAU-4387","DAU-4408","DAU-4434","DAU-4442","DAU-4443","DAU-4469","DAU-4479","DAU-4499","DAU-4506","DAU-4507","DAU-4572","DAU-4623","DAU-4676","DAU-4807","DAU-4878","DAU-4901","DAU-4995","DAU-5073","DAU-5088","DAU-5089","DAU-5124","DAU-5135","MAJ-140","MAJ-201","MAJ-305","MAJ-306","MAJ-533","MAJ-742","MAJ-754","MAJ-981","MAJ-1031","MAJ-1244","MAJ-1345","MAJ-1389","MAJ-1402","MAJ-1413","MAJ-1591","MAJ-1667","MAJ-1760","MAJ-1888","MAJ-1906","MAJ-1989","MAJ-2002","MAJ-2027","MAJ-2070","MAJ-2264","MAJ-2281","MAJ-2298","MAJ-2333","MAJ-2336","MAJ-2428","MAJ-2513","MAJ-2547","MAJ-2578","MAJ-2588","MAJ-2596","MAJ-2612","MAJ-2625","MAJ-2638","MAJ-2840","MAJ-2844","MAJ-2845","MAJ-2846","MAJ-2848","MAJ-2877","MAJ-2907","MAJ-2909","MAJ-2942","MAJ-2946","MAJ-3025","MAJ-3055","MAJ-3074","MAJ-3140","MAJ-3156","MAJ-3272","MAJ-3299","MAJ-3334","MAJ-3503","MAJ-3532","MAJ-3544","MAJ-3545","MAJ-3664","MAJ-3761","MAJ-3949","MAJ-4001","MAJ-4075","MAJ-4187","MAJ-4316","MAJ-4323","MUS-23","MUS-24","MUS-26","MUS-54","MUS-179","MUS-211","MUS-212","MUS-321","MUS-327","MUS-744","MUS-1012","MUS-1046","MUS-1056","MUS-1089","MUS-1371","MUS-1413","MUS-1418","MUS-1421","MUS-1425","MUS-1427","MUS-1435","MUS-1806","MUS-1819","MUS-1881","MUS-1973","MUS-2010","MUS-2275","MUS-2307","MUS-2312","MUS-2327","MUS-2539","MUS-2821","MUS-2828","MUS-2888","MUS-2953","MUS-3045","MUS-3116","MUS-3122","MUS-3206","MUS-3237","MUS-3289","MUS-3290","MUS-3295","MUS-3299","MUS-3547","MUS-3607","MUS-3611","MUS-3617","MUS-3625","MUS-3648","MUS-3891","MUS-3910","MUS-3936","MUS-3992","MUS-4099","MUS-4100","MUS-4119","MUS-4200","MUS-4212","MUS-4236","MUS-4243","MUS-4246","MUS-4247","MUS-4279","MUS-4282","MUS-4284","MUS-4293","MUS-4315","MUS-4403","MUS-4404","MUS-4405","MUS-4418","MUS-4421","MUS-4423","MUS-4440","MUS-4464","MUS-4465","MUS-4466","MUS-4471","MUS-4498","MUS-4527","MUS-4533","MUS-4586","MUS-4587","MUS-4588","MUS-4633","MUS-4635","MUS-4754","MUS-4849","MUS-4969","MUS-4970","MUS-5066","MUS-5388","MUS-5403","MUS-5404","MUS-5545","MUS-5648","MUS-5749","MUS-6135","MUS-6138","MUS-6141","MUS-6142","MUS-6181","MUS-6185","MUS-6193","MUS-6199","MUS-6204","MUS-6214","MUS-6216","MUS-6220","MUS-6221","MUS-6222","MUS-6259","MUS-6261","MUS-6264","MUS-6360","MUS-6361","MUS-6498","MUS-6760","MUS-6763","MUS-6943","MUS-7106","MUS-7122","MUS-7143","MUS-7240","NAS-4","NAS-165","NAS-201","NAS-306","NAS-307","NAS-350","NAS-521","NAS-654","NAS-703","NAS-836","NAS-863","NAS-1073","NAS-1076","NAS-1077","NAS-1080","NAS-1499","NAS-1618","NAS-1845","NAS-1960","NAS-2096","NAS-2097","NAS-2234","NAS-2282","NAS-2465","NAS-2548","NAS-2556","NAS-2580","NAS-2582","NAS-2598","NAS-2614","NAS-2637","NAS-2640","NAS-2643","NAS-2644","NAS-2721","NAS-2827","NAS-3044","NAS-3067","NAS-3185","NAS-3357","NAS-3361","NAS-3374","NAS-3421","NAS-3470","NAS-3474","NAS-3475","NAS-3482","NAS-3483","NAS-3485","NAS-3520","NAS-3522","NAS-3523","NAS-3549","NAS-3759","NAS-3774","NAS-3829","NAS-3984","NAS-4025","NAS-4026","NAS-4027","NAS-4029","NAS-4030","NAS-4031","NAS-4032","NAS-4033","NAS-4035","NAS-4183","NAS-4231","NAS-4249","NAS-4252","NAS-4317","NAS-4345","NAS-4348","NAS-4384","NAS-4457","NAS-4652","NAS-4672","NAS-4685","NAS-4706","NAS-4719","NAS-4727","NAS-4775","NAS-4780","NAS-4817","NAS-4818","NAS-4819","NAS-4825","NAS-4826","NAS-4829","NAS-4833","NAS-4834","NAS-4835","NAS-4836","NAS-4837","NAS-4838","NAS-4839","NAS-4874","NAS-4887","NAS-4888","NAS-4891","NAS-4892","NAS-4894","NAS-4900","NAS-4903","NAS-4958","NAS-5030","NAS-5090","NAS-5118","NAS-5381","NAS-5385","NAS-5386","NAS-5388","NAS-5389","NAS-5390","NAS-5391","NAS-5404","NAS-5412","NAS-5706","TIR-72","TIR-230","TIR-323","TIR-654","TIR-713","TIR-737","TIR-886","TIR-930","TIR-1146","TIR-1277","TIR-1410","TIR-1435","TIR-1436","TIR-1558","TIR-1565","TIR-1605","TIR-1610","TIR-1689","TIR-1694","TIR-1851","TIR-2017","TIR-2049","TIR-2131","TIR-2214","TIR-2230","TIR-2243","TIR-2442","TIR-2465","TIR-2612","TIR-2781","TIR-2925","TIR-3030","TIR-3116","TIR-3130","TIR-3180","TIR-3222","TIR-3247","TIR-3251","TIR-3252","TIR-3273","TIR-3302","TIR-3303","TIR-3307"],
"গোলামরা":["BUK-5992","DAU-2718","TIR-2378"],
"গোশতবিশিষ্ট":["DAU-2242"],
"গোশতকে":["BUK-3546","DAU-2696"],
"গোলামকেও":["MUS-4606","TIR-1712"],
"গোশতের":["BUK-50","BUK-426","BUK-891","BUK-907","BUK-917","BUK-1408","BUK-2400","BUK-3097","BUK-3098","BUK-3172","BUK-3546","BUK-3558","BUK-4336","BUK-4430","BUK-4810","BUK-4899","BUK-5023","BUK-5036","BUK-5158","BUK-5172","BUK-5512","DAU-182","DAU-185","DAU-188","DAU-259","DAU-2791","MAJ-3137","MAJ-3154","MAJ-3179","MAJ-3192","MAJ-3274","MAJ-3308","MAJ-3310","MAJ-3361","MUS-377","MUS-2268","MUS-2269","MUS-2821","MUS-3644","MUS-4517","MUS-4909","MUS-4916","MUS-4919","MUS-5861","MUS-6085","MUS-6489","MUS-7112","NAS-2587","NAS-4395","NAS-4396","NAS-4397","NAS-4425","TIR-612","TIR-1839","TIR-2539"],
"গোত্রপ্রধান":["BUK-4641"],
"গোলামটি":["BUK-2255","BUK-2356","BUK-2363","BUK-2364","BUK-2367","BUK-2851","BUK-3435","BUK-3915","BUK-4051","BUK-5066","BUK-6259","BUK-6478","DAU-3507","MUS-211","MUS-1099","MUS-3562","MUS-4042","TIR-1222","TIR-1350","TIR-1351","TIR-1352","TIR-1953","TIR-3318"],
"গোলামদেরকে":["MUS-7241"],
"গোত্রসমুহ":["BUK-3116"],
"গোঁপ":["DAU-4150"],
"গোলামদের":["DAU-2034","DAU-2294","DAU-2691","DAU-2718","DAU-2941","DAU-2942","DAU-3475","DAU-3917","DAU-3920","MUS-1770","MUS-5414","NAS-3534","TIR-1310","TIR-1368"],
"গোঁফ":["BUK-5468","BUK-5469","BUK-5471","BUK-5472","BUK-5473","BUK-5860","DAU-53","DAU-188","DAU-2780","DAU-4151","DAU-4152","MUS-490","MUS-491","MUS-492","MUS-493","MUS-494","MUS-496","MUS-497","NAS-9","NAS-10","NAS-11","NAS-12","NAS-13","NAS-15","NAS-4366","NAS-5045","NAS-5225"],
"গোলপাত্র":["TIR-2476"],
"গোলা":["BUK-3140","BUK-4398"],
"গোলাস":["MAJ-2530"],
"গোয়েন্দাগিরির":["BUK-3700"],
"গোদের":["MUS-5655"],
"গোরস্তানে":["TIR-737"],
"গোলযোগ":["BUK-1697","DAU-4251"],
"গোলার":["BUK-3757"],
"গোয়েন্দাগিরী":["BUK-5638"],
"গোলাম":["BUK-92","BUK-165","BUK-435","BUK-436","BUK-659","BUK-935","BUK-996","BUK-1379","BUK-1415","BUK-1416","BUK-1424","BUK-1679","BUK-1742","BUK-1813","BUK-1867","BUK-2128","BUK-2222","BUK-2255","BUK-2287","BUK-2294","BUK-2306","BUK-2329","BUK-2330","BUK-2339","BUK-2340","BUK-2351","BUK-2352","BUK-2353","BUK-2354","BUK-2355","BUK-2356","BUK-2357","BUK-2358","BUK-2359","BUK-2360","BUK-2363","BUK-2364","BUK-2371","BUK-2378","BUK-2382","BUK-2383","BUK-2384","BUK-2385","BUK-2386","BUK-2391","BUK-2394","BUK-2395","BUK-2399","BUK-2408","BUK-2415","BUK-2421","BUK-2423","BUK-2448","BUK-2472","BUK-2519","BUK-2563","BUK-2564","BUK-2583","BUK-2623","BUK-2638","BUK-2688","BUK-2758","BUK-2803","BUK-2851","BUK-2873","BUK-3063","BUK-3203","BUK-3398","BUK-3435","BUK-3440","BUK-3467","BUK-3487","BUK-3492","BUK-3534","BUK-3536","BUK-3564","BUK-3625","BUK-3635","BUK-3701","BUK-3710","BUK-3735","BUK-3793","BUK-3799","BUK-3915","BUK-3927","BUK-4031","BUK-4051","BUK-4110","BUK-4241","BUK-4420","BUK-4548","BUK-4712","BUK-4717","BUK-4743","BUK-4809","BUK-4911","BUK-4912","BUK-4964","BUK-5041","BUK-5658","BUK-5832","BUK-5884","BUK-5961","BUK-5962","BUK-6252","BUK-6253","BUK-6258","BUK-6264","BUK-6284","BUK-6368","BUK-6395","BUK-6438","BUK-6442","BUK-6478","BUK-6480","BUK-6625","BUK-6741","BUK-6743","BUK-6793","BUK-6868","BUK-7045","DAU-43","DAU-329","DAU-588","DAU-1051","DAU-1192","DAU-1273","DAU-1364","DAU-1367","DAU-1513","DAU-1517","DAU-1643","DAU-2034","DAU-2057","DAU-2075","DAU-2182","DAU-2185","DAU-2269","DAU-2271","DAU-2359","DAU-2362","DAU-2373","DAU-2410","DAU-2428","DAU-2658","DAU-2672","DAU-2689","DAU-2690","DAU-2691","DAU-2702","DAU-2741","DAU-2776","DAU-2868","DAU-2869","DAU-2873","DAU-2892","DAU-2895","DAU-2907","DAU-2976","DAU-2978","DAU-3003","DAU-3051","DAU-3179","DAU-3216","DAU-3325","DAU-3394","DAU-3397","DAU-3466","DAU-3473","DAU-3474","DAU-3475","DAU-3476","DAU-3504","DAU-3505","DAU-3507","DAU-3626","DAU-3899","DAU-3904","DAU-3906","DAU-3912","DAU-3914","DAU-3916","DAU-3917","DAU-3919","DAU-3920","DAU-3923","DAU-3927","DAU-4019","DAU-4040","DAU-4061","DAU-4107","DAU-4165","DAU-4309","DAU-4337","DAU-4360","DAU-4448","DAU-4499","DAU-4503","DAU-4505","DAU-4513","DAU-4534","DAU-4552","DAU-4711","DAU-4807","DAU-4991","DAU-4993","DAU-5035","DAU-5047","DAU-5076","DAU-5077","DAU-5078","MAJ-42","MAJ-1284","MAJ-1285","MAJ-1671","MAJ-1811","MAJ-1812","MAJ-1959","MAJ-2082","MAJ-2089","MAJ-2186","MAJ-2196","MAJ-2211","MAJ-2212","MAJ-2243","MAJ-2244","MAJ-2249","MAJ-2251","MAJ-2336","MAJ-2345","MAJ-2376","MAJ-2512","MAJ-2519","MAJ-2522","MAJ-2523","MAJ-2529","MAJ-2530","MAJ-2549","MAJ-2680","MAJ-2812","MAJ-2847","MAJ-2855","MAJ-2933","MAJ-3117","MAJ-3691","MAJ-3719","MAJ-3798","MAJ-3799","MAJ-3810","MAJ-3867","MUS-152","MUS-211","MUS-260","MUS-431","MUS-609","MUS-744","MUS-1216","MUS-1218","MUS-1222","MUS-1303","MUS-2067","MUS-2240","MUS-2241","MUS-2339","MUS-2466","MUS-2469","MUS-2503","MUS-2504","MUS-2506","MUS-2507","MUS-2542","MUS-2874","MUS-2969","MUS-2971","MUS-2992","MUS-3199","MUS-3538","MUS-3540","MUS-3761","MUS-3897","MUS-3935","MUS-3964","MUS-3968","MUS-4032","MUS-4033","MUS-4035","MUS-4158","MUS-4169","MUS-4172","MUS-4176","MUS-4178","MUS-4179","MUS-4188","MUS-4191","MUS-4192","MUS-4242","MUS-4243","MUS-4249","MUS-4527","MUS-4560","MUS-4571","MUS-4607","MUS-4608","MUS-4610","MUS-4951","MUS-4966","MUS-5235","MUS-5286","MUS-5504","MUS-5644","MUS-5680","MUS-5798","MUS-5913","MUS-6111","MUS-6115","MUS-6168","MUS-6178","MUS-6189","MUS-6318","MUS-6320","MUS-6346","MUS-6385","MUS-6598","MUS-6760","MUS-7119","MUS-7144","MUS-7240","MUS-7241","NAS-238","NAS-312","NAS-695","NAS-861","NAS-1340","NAS-1356","NAS-1484","NAS-1583","NAS-2469","NAS-2470","NAS-2471","NAS-2472","NAS-2473","NAS-2474","NAS-2502","NAS-2503","NAS-2504","NAS-2505","NAS-2506","NAS-2510","NAS-2517","NAS-2539","NAS-2614","NAS-2922","NAS-3053","NAS-3124","NAS-3146","NAS-3147","NAS-3178","NAS-3431","NAS-3654","NAS-3657","NAS-3829","NAS-3891","NAS-3940","NAS-4037","NAS-4051","NAS-4052","NAS-4053","NAS-4054","NAS-4055","NAS-4056","NAS-4057","NAS-4621","NAS-4654","NAS-4751","NAS-4954","NAS-5223","TIR-360","TIR-381","TIR-382","TIR-671","TIR-672","TIR-673","TIR-722","TIR-1111","TIR-1112","TIR-1117","TIR-1203","TIR-1242","TIR-1263","TIR-1287","TIR-1368","TIR-1371","TIR-1379","TIR-1416","TIR-1563","TIR-1602","TIR-1711","TIR-1963","TIR-1992","TIR-2059","TIR-2109","TIR-2114","TIR-2126","TIR-2299","TIR-2311","TIR-2567","TIR-2779","TIR-3164","TIR-3299","TIR-3468","TIR-3471","TIR-3553","TIR-3563"],
"গোড়া":["NAS-4373","NAS-4374","NAS-4375"],
"গোড়ালিগুলোর":["BUK-58","MUS-463","MUS-465","MUS-466","MUS-468"],
"গোপনকারিনী":["MAJ-4030"],
"গোত্রগুলোকে":["BUK-3520"],
"গোত্রকে":["BUK-337","BUK-2375","BUK-2731","BUK-2736","BUK-3567","BUK-3735","BUK-3852","BUK-4050","BUK-4233","BUK-4308","BUK-4543","BUK-5767","BUK-5955","DAU-3667","MAJ-1243","MAJ-3949","MUS-4886","MUS-5749","MUS-6135","MUS-6196","MUS-6199","MUS-6202","MUS-6204","MUS-6205","MUS-6207","NAS-3926"],
"গোশতে":["BUK-3637","DAU-2697","DAU-4448","MUS-891","MUS-1661","MUS-5518","TIR-3419"],
"গোভ্রের":["DAU-453"],
"গোলমও":["TIR-2676"],
"গোনাহসমূহ":["BUK-1882","BUK-1883","MUS-6325","MUS-6336"],
"গোমরাহ্":["DAU-1903","DAU-2115"],
"গোত্রীয়রা":["BUK-2607"],
"গোয়েন্দাকে":["BUK-3868"],
"গোশতপিণ্ড":["BUK-6143","TIR-2140"],
"গোশতপেশি":["DAU-2641"],
"গোপনে":["BUK-506","BUK-565","BUK-627","BUK-1338","BUK-1340","BUK-2285","BUK-3039","BUK-3947","BUK-4090","BUK-4749","BUK-7017","BUK-7038","DAU-201","DAU-1297","DAU-1329","DAU-1333","DAU-2078","DAU-2643","DAU-2645","DAU-4994","MAJ-1081","MAJ-1355","MAJ-1621","MAJ-2012","MAJ-2867","MAJ-4029","MAJ-4200","MAJ-4226","MAJ-4245","MUS-275","MUS-973","MUS-4962","MUS-6091","NAS-578","NAS-1666","NAS-2563","NAS-2572","NAS-3796","NAS-3984","NAS-4423","NAS-5379","TIR-876","TIR-2252","TIR-2387","TIR-2394","TIR-2568","TIR-2569","TIR-2919","TIR-2997","TIR-3009","TIR-3149","TIR-3247","TIR-3258","TIR-3418","TIR-3421"],
"গোছল":["MUS-6039"],
"গোত্রটির":["BUK-3943","BUK-7045"],
"গোত্রগুলোর":["BUK-3144","BUK-3266","BUK-3519","BUK-3535"],
"গোমরাহী":["BUK-6627"],
"গোমরা":["BUK-6280"],
"গো":["BUK-3210","BUK-4282","BUK-4377","BUK-4391"],
"গোছাসহ":["DAU-858"],
"গোছা":["BUK-1063","BUK-3748","DAU-4045","DAU-4071","DAU-4120","DAU-4146","DAU-4149","DAU-4258","MAJ-60","MAJ-456","MAJ-460","MAJ-2481","MAJ-2482","MAJ-2483","MAJ-2929","MAJ-3509","MAJ-3559","MAJ-3560","MAJ-3561","MAJ-3573","MUS-473","MUS-5158","MUS-5992","MUS-7041","MUS-7042","MUS-7119","NAS-3240","NAS-3462","NAS-3463","NAS-3474","NAS-3475","NAS-5092","TIR-1790"],
"গোত্রীয়":["NAS-3940","NAS-4706"],
"গোবর":["BUK-157","BUK-158","BUK-496","BUK-2215","BUK-2656","BUK-2663","BUK-3581","DAU-7","DAU-39","DAU-41","MAJ-313","MAJ-316","MAJ-2084","MUS-499","MUS-500","MUS-501","NAS-39","NAS-40","NAS-42","NAS-308","NAS-3506","NAS-3537","NAS-3542","NAS-3543","NAS-3544","NAS-3545","NAS-5066","TIR-17","TIR-18","TIR-3258"],
"গোয়েন্দা":["BUK-2831","BUK-3786","BUK-3868","DAU-198","DAU-4274","DAU-4275","DAU-4277"],
"গোলমেলে":["BUK-4514"],
"গোষ্ঠীর":["BUK-3277","BUK-4290","MAJ-256","MAJ-3960","MUS-5543","MUS-7033","MUS-7106","TIR-3343"],
"গোপনীয়":["BUK-100","BUK-3715","BUK-5849","MAJ-1461","MAJ-1462","MUS-6085","MUS-6155"],
"গোসলকালে":["MUS-613"],
"গোশতপূর্ণ":["BUK-4857"],
"গোত্র":["BUK-39","BUK-51","BUK-113","BUK-498","BUK-791","BUK-880","BUK-952","BUK-1395","BUK-1495","BUK-2150","BUK-2212","BUK-2485","BUK-2736","BUK-2904","BUK-3242","BUK-3244","BUK-3245","BUK-3248","BUK-3263","BUK-3264","BUK-3265","BUK-3267","BUK-3269","BUK-3275","BUK-3405","BUK-3417","BUK-3505","BUK-3518","BUK-3520","BUK-3535","BUK-3648","BUK-3735","BUK-3790","BUK-3794","BUK-3824","BUK-3835","BUK-3868","BUK-3879","BUK-3952","BUK-3971","BUK-4001","BUK-4016","BUK-4017","BUK-4018","BUK-4028","BUK-4030","BUK-4031","BUK-4049","BUK-4050","BUK-4247","BUK-4256","BUK-4590","BUK-4641","BUK-5121","BUK-5894","BUK-6009","BUK-6194","BUK-6432","BUK-6632","BUK-6749","DAU-1983","DAU-2028","DAU-2294","DAU-2517","DAU-2607","DAU-2961","DAU-3279","DAU-4203","MAJ-754","MAJ-1345","MAJ-2612","MAJ-2649","MAJ-3074","MAJ-3952","MUS-23","MUS-24","MUS-42","MUS-87","MUS-1430","MUS-4099","MUS-4244","MUS-4405","MUS-4425","MUS-4440","MUS-4639","MUS-6135","MUS-6187","MUS-6193","MUS-6196","MUS-6197","MUS-6198","MUS-6199","MUS-6206","MUS-6207","MUS-6212","MUS-6213","MUS-6217","MUS-6219","MUS-7119","NAS-2915","NAS-3765","NAS-3971","NAS-3972","NAS-4028","NAS-4271","NAS-4706","NAS-4732","NAS-4733","NAS-5399","TIR-1588","TIR-1854","TIR-2144","TIR-2222","TIR-3086","TIR-3226","TIR-3532","TIR-3607","TIR-3608"],
"গোলাকারে":["MUS-1952"],
"গোশতগুলো":["BUK-3882","MUS-4942"],
"গোফ":["NAS-3046"],
"গোত্রপ্রীতির":["MUS-4633","MUS-4639"],
"গোল":["BUK-4915","DAU-4748","NAS-3390","NAS-3499","TIR-322","TIR-2753","TIR-3218","TIR-3379"],
"গোপনও":["MAJ-2505","TIR-3318"],
"গোষ্ঠির":["TIR-3255"],
"গোরস্থানেপৌছে":["MAJ-1528"],
"গোছার":["BUK-3314","BUK-3744","DAU-635","DAU-1823","DAU-2218","DAU-4040","DAU-4049","MAJ-2208","MAJ-2932","MAJ-3569","MAJ-3570","MAJ-3571","MAJ-3572","MAJ-3573","MAJ-3574","MAJ-3576","MUS-472","MUS-4527","MUS-6884","NAS-5009","NAS-5328","TIR-2524"],
"গোমায়ম":["BUK-2547"],
"গোত্রেরই":["BUK-3126"],
"গোড়ার":["BUK-3888"],
"গোরস্থানে":["BUK-3435","MAJ-1628"],
"গোশতপিন্ডের":["MAJ-76"],
"গোলামাদেরকে":["NAS-3533"],
"গোপনকারীর":["MUS-4533"],
"গোলামটাই":["BUK-2340","BUK-2359"],
"গোমরাহীর":["BUK-1088"],
"গোষ্ঠীকে":["BUK-1285","DAU-1690"],
"গোষ্ঠী":["MUS-6170","MUS-7155"],
"গোঁড়ায়":["MUS-1099","MUS-4527"],
"গোত্রসমূহের":["BUK-2946","BUK-5338","MUS-6197","TIR-3607"],
"গোষ্ঠি":["TIR-2847"],
"গোত্রস্থিত":["DAU-2252","DAU-2400"],
"গোত্রবাদে":["MAJ-3948"],
"গোত্রপতি":["BUK-2485"],
"গোত্রেবাদের":["MAJ-3949"],
"গোসত":["BUK-1361"],
"গোশতবহুল":["BUK-3835","BUK-5163","BUK-5486","BUK-5487","BUK-6730","MAJ-2067","MUS-7046","MUS-7047","MUS-7049","MUS-7050","NAS-849"],
"গোসলই":["DAU-342","MAJ-599","MAJ-1091"],
"গোত্রগুলিকে":["BUK-3275"],
"গোসলের":["BUK-255","BUK-257","BUK-259","BUK-263","BUK-264","BUK-271","BUK-273","BUK-274","BUK-308","BUK-321","BUK-331","BUK-337","BUK-341","BUK-653","BUK-834","BUK-837","BUK-1182","BUK-3318","DAU-53","DAU-102","DAU-206","DAU-214","DAU-215","DAU-235","DAU-241","DAU-242","DAU-245","DAU-246","DAU-249","DAU-250","DAU-251","DAU-255","DAU-279","DAU-290","DAU-291","DAU-292","DAU-295","DAU-301","DAU-351","DAU-353","DAU-359","DAU-376","DAU-3848","DAU-4126","DAU-4132","DAU-5095","MAJ-371","MAJ-372","MAJ-466","MAJ-572","MAJ-573","MAJ-579","MAJ-580","MAJ-589","MAJ-594","MAJ-604","MAJ-609","MAJ-613","MAJ-642","MAJ-2087","MUS-615","MUS-634","MUS-637","MUS-638","MUS-640","MUS-645","MUS-1436","NAS-231","NAS-239","NAS-247","NAS-253","NAS-254","NAS-326","NAS-408","NAS-415","NAS-419","NAS-425","NAS-430","NAS-532","NAS-1391","NAS-1887","TIR-103","TIR-105","TIR-107","TIR-110","TIR-111","TIR-2924","TIR-3221"],
"গোলামের":["BUK-1378","BUK-1423","BUK-2306","BUK-2329","BUK-2330","BUK-2339","BUK-2351","BUK-2352","BUK-2355","BUK-2356","BUK-2357","BUK-2359","BUK-2368","BUK-2377","BUK-2385","BUK-2391","BUK-2428","BUK-2472","BUK-2827","BUK-3427","BUK-3435","BUK-3880","BUK-4825","BUK-4899","BUK-4912","BUK-6258","BUK-6395","DAU-185","DAU-388","DAU-1818","DAU-2269","DAU-2896","DAU-2987","DAU-3325","DAU-3398","DAU-3399","DAU-3421","DAU-3893","DAU-3896","DAU-3897","DAU-3899","DAU-3900","DAU-3902","DAU-3905","DAU-3906","DAU-3907","DAU-3915","DAU-3921","DAU-3924","DAU-4067","DAU-4068","DAU-4120","DAU-4212","DAU-4337","DAU-4450","DAU-4452","DAU-4453","DAU-4512","DAU-5049","DAU-5067","DAU-5068","MAJ-1790","MAJ-1813","MAJ-2031","MAJ-2081","MAJ-2242","MAJ-2243","MAJ-2296","MAJ-2527","MAJ-2528","MAJ-2869","MAJ-3719","MAJ-3958","MUS-2148","MUS-3190","MUS-3562","MUS-3648","MUS-3761","MUS-3968","MUS-4167","MUS-4169","MUS-4174","MUS-4177","MUS-4179","MUS-4180","MUS-4183","MUS-4185","MUS-4186","MUS-5415","MUS-5416","MUS-7240","NAS-2507","NAS-3532","NAS-3940","NAS-4698","NAS-4810","TIR-1017","TIR-1207","TIR-1242","TIR-1262","TIR-1287","TIR-1350","TIR-1351","TIR-1352","TIR-1602","TIR-3343"],
"গোড়ার":["NAS-4376"],
"গোসল":["BUK-132","BUK-168","BUK-201","BUK-238","BUK-246","BUK-247","BUK-248","BUK-249","BUK-250","BUK-251","BUK-254","BUK-256","BUK-258","BUK-259","BUK-260","BUK-261","BUK-262","BUK-270","BUK-272","BUK-275","BUK-277","BUK-278","BUK-279","BUK-281","BUK-286","BUK-287","BUK-289","BUK-292","BUK-295","BUK-308","BUK-309","BUK-314","BUK-316","BUK-319","BUK-321","BUK-324","BUK-337","BUK-350","BUK-503","BUK-611","BUK-612","BUK-653","BUK-816","BUK-833","BUK-835","BUK-836","BUK-837","BUK-838","BUK-839","BUK-840","BUK-841","BUK-850","BUK-851","BUK-852","BUK-857","BUK-864","BUK-873","BUK-1080","BUK-1106","BUK-1170","BUK-1180","BUK-1181","BUK-1183","BUK-1184","BUK-1185","BUK-1187","BUK-1189","BUK-1191","BUK-1192","BUK-1193","BUK-1194","BUK-1200","BUK-1223","BUK-1262","BUK-1460","BUK-1478","BUK-1720","BUK-1721","BUK-1729","BUK-1730","BUK-1731","BUK-1803","BUK-1806","BUK-1807","BUK-2489","BUK-2618","BUK-2947","BUK-3093","BUK-3153","BUK-3165","BUK-3240","BUK-3817","BUK-3822","BUK-3962","BUK-4033","BUK-5691","BUK-5727","BUK-6839","BUK-6985","DAU-27","DAU-61","DAU-68","DAU-69","DAU-77","DAU-81","DAU-87","DAU-92","DAU-93","DAU-95","DAU-98","DAU-206","DAU-210","DAU-211","DAU-214","DAU-215","DAU-216","DAU-217","DAU-218","DAU-219","DAU-226","DAU-231","DAU-234","DAU-235","DAU-236","DAU-237","DAU-238","DAU-239","DAU-240","DAU-241","DAU-243","DAU-244","DAU-245","DAU-246","DAU-247","DAU-250","DAU-254","DAU-255","DAU-274","DAU-275","DAU-277","DAU-278","DAU-279","DAU-280","DAU-281","DAU-284","DAU-285","DAU-286","DAU-287","DAU-288","DAU-289","DAU-290","DAU-291","DAU-293","DAU-294","DAU-296","DAU-297","DAU-298","DAU-299","DAU-300","DAU-301","DAU-302","DAU-303","DAU-305","DAU-316","DAU-321","DAU-332","DAU-333","DAU-334","DAU-336","DAU-337","DAU-340","DAU-341","DAU-342","DAU-343","DAU-344","DAU-345","DAU-346","DAU-347","DAU-348","DAU-351","DAU-352","DAU-353","DAU-354","DAU-355","DAU-359","DAU-429","DAU-1291","DAU-1437","DAU-1743","DAU-1744","DAU-1785","DAU-1863","DAU-1903","DAU-2381","DAU-2670","DAU-2987","DAU-3124","DAU-3127","DAU-3128","DAU-3131","DAU-3132","DAU-3133","DAU-3143","DAU-3146","DAU-3147","DAU-3226","DAU-3840","DAU-3848","DAU-3971","DAU-4126","DAU-4375","DAU-4381","DAU-5095","MAJ-267","MAJ-268","MAJ-269","MAJ-355","MAJ-370","MAJ-371","MAJ-374","MAJ-375","MAJ-376","MAJ-377","MAJ-378","MAJ-379","MAJ-380","MAJ-465","MAJ-466","MAJ-467","MAJ-478","MAJ-504","MAJ-506","MAJ-534","MAJ-535","MAJ-572","MAJ-573","MAJ-575","MAJ-576","MAJ-577","MAJ-580","MAJ-581","MAJ-582","MAJ-583","MAJ-588","MAJ-589","MAJ-590","MAJ-598","MAJ-600","MAJ-601","MAJ-602","MAJ-603","MAJ-604","MAJ-605","MAJ-606","MAJ-607","MAJ-608","MAJ-609","MAJ-610","MAJ-611","MAJ-612","MAJ-614","MAJ-615","MAJ-623","MAJ-624","MAJ-625","MAJ-626","MAJ-627","MAJ-641","MAJ-642","MAJ-646","MAJ-663","MAJ-664","MAJ-1087","MAJ-1088","MAJ-1089","MAJ-1091","MAJ-1097","MAJ-1098","MAJ-1220","MAJ-1315","MAJ-1316","MAJ-1397","MAJ-1458","MAJ-1459","MAJ-1461","MAJ-1462","MAJ-1463","MAJ-1464","MAJ-1465","MAJ-1466","MAJ-1467","MAJ-1468","MAJ-1578","MAJ-1703","MAJ-1704","MAJ-2911","MAJ-2912","MAJ-2913","MAJ-2934","MAJ-3074","MAJ-3084","MAJ-3509","MAJ-3604","MUS-309","MUS-369","MUS-549","MUS-550","MUS-551","MUS-576","MUS-596","MUS-598","MUS-602","MUS-604","MUS-605","MUS-608","MUS-611","MUS-614","MUS-618","MUS-620","MUS-621","MUS-622","MUS-623","MUS-624","MUS-625","MUS-626","MUS-627","MUS-630","MUS-631","MUS-632","MUS-635","MUS-636","MUS-639","MUS-640","MUS-641","MUS-642","MUS-643","MUS-645","MUS-648","MUS-649","MUS-652","MUS-653","MUS-657","MUS-658","MUS-660","MUS-663","MUS-668","MUS-669","MUS-671","MUS-676","MUS-678","MUS-679","MUS-710","MUS-711","MUS-821","MUS-1245","MUS-1396","MUS-1397","MUS-1541","MUS-1542","MUS-1825","MUS-1829","MUS-1830","MUS-1832","MUS-1834","MUS-1836","MUS-1860","MUS-2039","MUS-2041","MUS-2044","MUS-2045","MUS-2047","MUS-2461","MUS-2762","MUS-2765","MUS-2767","MUS-2768","MUS-2769","MUS-2771","MUS-2772","MUS-2779","MUS-2789","MUS-5933","MUS-5934","MUS-6171","NAS-58","NAS-72","NAS-73","NAS-188","NAS-189","NAS-190","NAS-191","NAS-192","NAS-193","NAS-194","NAS-195","NAS-196","NAS-197","NAS-198","NAS-199","NAS-202","NAS-203","NAS-204","NAS-205","NAS-206","NAS-207","NAS-209","NAS-210","NAS-211","NAS-214","NAS-215","NAS-218","NAS-219","NAS-220","NAS-221","NAS-222","NAS-223","NAS-224","NAS-225","NAS-226","NAS-227","NAS-228","NAS-229","NAS-230","NAS-232","NAS-233","NAS-234","NAS-235","NAS-236","NAS-237","NAS-238","NAS-239","NAS-240","NAS-241","NAS-244","NAS-245","NAS-246","NAS-248","NAS-249","NAS-251","NAS-252","NAS-255","NAS-270","NAS-292","NAS-326","NAS-332","NAS-345","NAS-346","NAS-347","NAS-348","NAS-350","NAS-351","NAS-352","NAS-353","NAS-354","NAS-355","NAS-356","NAS-357","NAS-360","NAS-361","NAS-364","NAS-392","NAS-396","NAS-397","NAS-398","NAS-399","NAS-400","NAS-404","NAS-405","NAS-406","NAS-407","NAS-409","NAS-410","NAS-411","NAS-412","NAS-413","NAS-414","NAS-415","NAS-416","NAS-418","NAS-419","NAS-420","NAS-422","NAS-423","NAS-424","NAS-426","NAS-427","NAS-429","NAS-463","NAS-793","NAS-810","NAS-835","NAS-1379","NAS-1380","NAS-1382","NAS-1391","NAS-1401","NAS-1409","NAS-1683","NAS-1884","NAS-1885","NAS-1888","NAS-1889","NAS-1890","NAS-1893","NAS-1896","NAS-1897","NAS-1907","NAS-2010","NAS-2407","NAS-2409","NAS-2665","NAS-2666","NAS-2667","NAS-2715","NAS-2716","NAS-2763","NAS-2764","NAS-2765","NAS-2857","NAS-2858","NAS-2859","NAS-2860","NAS-3399","NAS-5126","TIR-56","TIR-62","TIR-65","TIR-96","TIR-103","TIR-104","TIR-108","TIR-109","TIR-111","TIR-112","TIR-113","TIR-114","TIR-115","TIR-118","TIR-121","TIR-122","TIR-123","TIR-126","TIR-127","TIR-128","TIR-129","TIR-131","TIR-474","TIR-492","TIR-493","TIR-494","TIR-496","TIR-497","TIR-499","TIR-528","TIR-605","TIR-611","TIR-777","TIR-832","TIR-854","TIR-948","TIR-954","TIR-990","TIR-993","TIR-1761","TIR-2068","TIR-2734","TIR-2868","TIR-2924","TIR-3221","TIR-3535","TIR-3536"],
"গোত্রটি":["BUK-1395","BUK-3260","DAU-2161","DAU-4434"],
"গোষ্ঠীরই":["BUK-3277"],
"গোত্রগুলো":["BUK-3253","BUK-3262","BUK-3265","BUK-3266","BUK-3646"],
"গোত্রদ্বয়":["BUK-3266"],
"গোছাদ্বয়ের":["MUS-1002"],
"গোলামটির":["DAU-5076","TIR-1351","TIR-1352","TIR-3318"],
"গোলামগণ":["NAS-1915"],
"গোড়ালিসমূহের":["MAJ-450","MAJ-451","MAJ-452","MAJ-453","MAJ-454","MAJ-455"],
"গোসলখানায়":["BUK-1807","BUK-4478","DAU-27","DAU-28","MAJ-304","MAJ-746","MAJ-747","MAJ-3749","MAJ-3750","NAS-36","TIR-21"],
"গোড়ালি":["BUK-3125","BUK-3126","BUK-3605","DAU-97","DAU-116","DAU-662","DAU-664","MAJ-450","MAJ-3580","MUS-351","MUS-463","MUS-6942"],
"গোত্রীয়":["BUK-51","BUK-569","BUK-630","BUK-972","BUK-1325","BUK-1465","BUK-1681","BUK-2485","BUK-3567","BUK-3674","BUK-3680","BUK-3835","BUK-5220","BUK-6347","BUK-6631","DAU-507","DAU-808","DAU-2529","MAJ-2635","MAJ-2646","MUS-315","MUS-316","MUS-320","MUS-6088","MUS-6763","MUS-6764","MUS-7106","TIR-1652","TIR-3248"],
"গোড়ালী":["BUK-96","BUK-3603","BUK-6392","BUK-6480","DAU-4174","MUS-4461","MUS-4462","MUS-5861","NAS-96","NAS-110","NAS-111","NAS-116","NAS-147","TIR-41","TIR-2424"],
"গোচরীভূত":["BUK-501","BUK-4398","DAU-2710","DAU-3798","MAJ-4226","TIR-3312"],
"গোস্বায়":["BUK-4480"],
"গোরস্থান":["TIR-2877"],
"গোবরের":["BUK-4598","DAU-38","MAJ-314","MAJ-2788","MUS-2162","MUS-2164","NAS-42"],
"গোলামকে":["BUK-659","BUK-871","BUK-2137","BUK-2306","BUK-2330","BUK-2360","BUK-2363","BUK-2367","BUK-2399","BUK-2472","BUK-2586","BUK-2842","BUK-6259","BUK-6299","BUK-6480","DAU-1080","DAU-2299","DAU-2689","DAU-3365","DAU-3394","DAU-3474","DAU-3896","DAU-3899","DAU-3916","DAU-3921","DAU-3924","DAU-4337","DAU-4338","DAU-4450","DAU-4451","DAU-5068","DAU-5069","DAU-5070","DAU-5074","DAU-5076","DAU-5078","MAJ-2062","MAJ-2474","MAJ-2527","MAJ-2679","MUS-2185","MUS-2186","MUS-3632","MUS-3853","MUS-3935","MUS-4153","MUS-4154","MUS-4155","MUS-4163","MUS-4186","MUS-4189","MUS-4191","MUS-4535","MUS-5136","NAS-740","NAS-4041","NAS-4653","TIR-1099","TIR-1222","TIR-1280","TIR-1953","TIR-1954","TIR-3318"],
"গোমরাহ":["BUK-101","DAU-1097","DAU-1098","MUS-6502"],
"গোসলে":["BUK-307","DAU-256","DAU-287","DAU-294","MAJ-270","MAJ-574","MAJ-578","MAJ-599","MAJ-2934","MUS-2760","NAS-231","NAS-264","NAS-265","NAS-428","NAS-1959","TIR-140"],
"গোপনই":["BUK-6915"],
"গোসলখানা":["DAU-9","DAU-492","MAJ-304","MAJ-745","MAJ-3748","MUS-4960","TIR-317","TIR-3130"],
"গোপণ":["DAU-2685"],
"গোত্রসমুহের":["MUS-6193"],
"গোলামও":["BUK-6867","MAJ-43","MUS-4180","MUS-4604","MUS-6346"],
"গোপন":["BUK-119","BUK-128","BUK-130","BUK-161","BUK-319","BUK-407","BUK-507","BUK-705","BUK-813","BUK-877","BUK-1054","BUK-1272","BUK-2196","BUK-2279","BUK-2280","BUK-2744","BUK-2745","BUK-2840","BUK-2923","BUK-3125","BUK-3154","BUK-3268","BUK-3325","BUK-3364","BUK-3470","BUK-3471","BUK-3489","BUK-3613","BUK-3625","BUK-3699","BUK-3771","BUK-3947","BUK-4076","BUK-4212","BUK-4257","BUK-4282","BUK-4328","BUK-4377","BUK-4391","BUK-4410","BUK-4424","BUK-4432","BUK-4453","BUK-4457","BUK-4491","BUK-4530","BUK-4747","BUK-4749","BUK-4768","BUK-4810","BUK-5385","BUK-5644","BUK-6234","BUK-6400","BUK-6915","BUK-6932","BUK-7006","BUK-7013","BUK-7023","BUK-7034","DAU-498","DAU-544","DAU-570","DAU-1332","DAU-1333","DAU-1374","DAU-1383","DAU-1586","DAU-1709","DAU-1718","DAU-2171","DAU-2184","DAU-2416","DAU-2541","DAU-2629","DAU-2707","DAU-2996","DAU-3423","DAU-3566","DAU-3567","DAU-3890","DAU-4040","DAU-4278","DAU-4303","DAU-4409","DAU-4738","DAU-4739","DAU-4813","DAU-4862","DAU-4967","DAU-4990","DAU-5124","MAJ-132","MAJ-139","MAJ-225","MAJ-261","MAJ-262","MAJ-263","MAJ-264","MAJ-265","MAJ-266","MAJ-297","MAJ-1387","MAJ-1621","MAJ-2011","MAJ-2544","MAJ-2546","MAJ-2604","MAJ-3354","MAJ-3871","MAJ-3873","MAJ-4030","MAJ-4172","MAJ-4205","MUS-26","MUS-229","MUS-336","MUS-337","MUS-435","MUS-1685","MUS-2128","MUS-3273","MUS-3562","MUS-3623","MUS-4314","MUS-4962","MUS-6085","MUS-6091","MUS-6092","MUS-6154","MUS-6174","MUS-6176","MUS-6342","MUS-6359","MUS-6720","MUS-6759","MUS-6760","MUS-6777","MUS-6949","MUS-7090","MUS-7215","MUS-7241","NAS-2041","NAS-3251","NAS-3262","NAS-3464","NAS-3558","NAS-3960","NAS-3965","NAS-3966","NAS-4179","NAS-4211","NAS-4458","NAS-4465","TIR-1174","TIR-1249","TIR-1431","TIR-1432","TIR-1673","TIR-1936","TIR-2038","TIR-2040","TIR-2387","TIR-2570","TIR-2627","TIR-2650","TIR-2945","TIR-2990","TIR-2991","TIR-3014","TIR-3036","TIR-3068","TIR-3104","TIR-3112","TIR-3115","TIR-3147","TIR-3207","TIR-3208","TIR-3247","TIR-3248","TIR-3278","TIR-3305","TIR-3369","TIR-3530","TIR-3539"],
"গোলামরূপেই":["BUK-2394"],
"গোধুম":["BUK-3012"],
"গোসলান্তে":["DAU-304"],
"গোত্রত্রয়":["BUK-3266"],
"গোত্রস্থি":["BUK-4196"],
"গোস্বার":["BUK-4812","MUS-3558","MUS-5426"],
"গোয়ার্তুমী":["MUS-99"],
"গোমরাহকারী":["DAU-1097"],
"গোলামী":["DAU-2691"],
"গোত্রবাদের":["MAJ-3948","MAJ-3949"],
"গোলামা":["BUK-2815"],
"গোচর":["NAS-1298","TIR-3374","TIR-3461"],
"গোলামে":["BUK-2358","DAU-3017","DAU-3473"],
"গোপনদোষ":["MUS-6304"],
"গোসলদানকারী":["MAJ-1467"],
"গোপনাঙ্গ":["MUS-5933"],
"গোসাপের":["NAS-4317","NAS-4318","NAS-4319"],
"গোড়া":["BUK-246","BUK-4047","DAU-2541","DAU-2794","MUS-313","MUS-4631","MUS-4931","MUS-5030","NAS-248","NAS-249","NAS-703","TIR-2589"],
"গোশত্‌":["BUK-3125"],
"গোসলও":["BUK-1265","BUK-1266","BUK-1271","BUK-3780","BUK-4012","DAU-70","MAJ-1514","TIR-1036"],
"গোছাবিশিষ্ট":["DAU-2250"]}