{"সর্বাধিক":["BUK-452","BUK-528","BUK-1064","BUK-1065","BUK-1083","BUK-1310","BUK-1803","BUK-2128","BUK-2691","BUK-2739","BUK-2826","BUK-3180","BUK-3243","BUK-3255","BUK-3333","BUK-3392","BUK-3413","BUK-3450","BUK-3476","BUK-3488","BUK-3490","BUK-3563","BUK-3587","BUK-3624","BUK-3694","BUK-3875","BUK-4197","BUK-4555","BUK-4634","BUK-5017","BUK-5070","BUK-5603","BUK-5607","BUK-5615","BUK-5773","BUK-5984","BUK-6045","BUK-6123","BUK-6145","BUK-6146","BUK-6147","BUK-6178","BUK-6269","BUK-6328","BUK-6470","BUK-6509","BUK-6553","BUK-6571","BUK-6697","BUK-6778","DAU-582","DAU-784","DAU-875","MAJ-20","MAJ-102","MAJ-154","MAJ-176","MAJ-1061","MAJ-1687","MAJ-1913","MAJ-1955","MAJ-2018","MAJ-2563","MAJ-2772","MAJ-2980","MAJ-3055","MAJ-3108","MAJ-3679","MAJ-3728","MAJ-3761","MAJ-3790","MAJ-4024","MAJ-4043","MAJ-4077","MAJ-4090","MAJ-4238","MAJ-4257","MAJ-4259","MAJ-4297","MUS-156","MUS-380","MUS-1612","MUS-1701","MUS-1703","MUS-1707","MUS-1794","MUS-2187","MUS-2293","MUS-2323","MUS-2328","MUS-2352","MUS-2460","MUS-2464","MUS-2493","MUS-2601","MUS-2611","MUS-3158","MUS-3341","MUS-4225","MUS-4513","MUS-4718","MUS-5347","MUS-5371","MUS-5402","MUS-5692","MUS-5693","MUS-5694","MUS-5695","MUS-5708","MUS-5840","MUS-5954","MUS-6047","MUS-6094","MUS-6109","MUS-6170","MUS-6197","MUS-6269","MUS-6519","MUS-6521","MUS-6595","MUS-6653","MUS-6677","MUS-6743","MUS-6760","MUS-6762","MUS-6809","MUS-6824","MUS-6829","MUS-6845","MUS-6846","MUS-6847","MUS-6861","MUS-6998","MUS-7003","MUS-7015","MUS-7016","MUS-7086","MUS-7094","MUS-7162","MUS-7205","NAS-1645","NAS-1655","NAS-1657","NAS-2352","NAS-3232","NAS-3285","NAS-3566","NAS-4166","NAS-5314","NAS-5355","NAS-5356","NAS-5363","TIR-883","TIR-1128","TIR-1216","TIR-1770","TIR-2446","TIR-2555","TIR-2840","TIR-3086","TIR-3102","TIR-3579"],
"সরক্ষণ":["DAU-410"],
"সরবে":["BUK-3748","MUS-775","MUS-777","TIR-2419"],
"সরকারের":["MAJ-1820"],
"সর্বসাধারণকে":["MUS-6779"],
"সর্বশেষ":["BUK-289","BUK-655","BUK-832","BUK-1310","BUK-1466","BUK-2749","BUK-3240","BUK-3241","BUK-3280","BUK-3283","BUK-3367","BUK-3604","BUK-4025","BUK-4250","BUK-4410","BUK-4532","BUK-4868","BUK-5872","BUK-5908","BUK-6109","BUK-6124","BUK-6171","BUK-6288","BUK-6370","BUK-6421","BUK-6560","BUK-6824","BUK-6931","BUK-6987","BUK-7003","BUK-7009","DAU-132","DAU-133","DAU-192","DAU-395","DAU-415","DAU-671","DAU-678","DAU-730","DAU-810","DAU-836","DAU-963","DAU-966","DAU-972","DAU-1018","DAU-1026","DAU-1046","DAU-1185","DAU-1194","DAU-1306","DAU-1338","DAU-1356","DAU-1438","DAU-1464","DAU-1972","DAU-2569","DAU-2593","DAU-3102","DAU-3628","DAU-3786","DAU-5066","MAJ-714","MAJ-906","MAJ-987","MAJ-988","MAJ-1001","MAJ-1083","MAJ-2826","MAJ-2921","MAJ-4077","MAJ-4287","MAJ-4290","MUS-348","MUS-357","MUS-358","MUS-1685","MUS-2039","MUS-2477","MUS-2821","MUS-3089","MUS-3090","MUS-3246","MUS-4007","MUS-4008","MUS-4009","MUS-4011","MUS-5894","MUS-5897","MUS-6199","MUS-7022","MUS-7106","MUS-7265","NAS-76","NAS-78","NAS-451","NAS-695","NAS-786","NAS-1834","NAS-4001","NAS-5610","TIR-3063","TIR-3400"],
"সরবো":["BUK-5294"],
"সরতে":["MAJ-1234","MUS-1982"],
"সরকারী":["BUK-2842","BUK-6181","BUK-6480","DAU-2935","DAU-4521","MUS-2179","MUS-3706","MUS-3949","MUS-4134"],
"সর্ববৃহৎ":["MAJ-3950","NAS-3637","NAS-4355"],
"সর্বসাধারণের":["MAJ-4014","MUS-4964"],
"সর্বতোভাবে":["BUK-3508","MUS-229"],
"সরাই":["MUS-6131"],
"সর্বোত্তমটি":["MAJ-3790","NAS-5004"],
"সর্বশেষটি":["DAU-1658","MUS-2172"],
"সরছে":["MUS-4527"],
"সরিয়েও":["DAU-2996"],
"সর্বপ্রথমে":["DAU-351","MUS-789"],
"সর্বসমক্ষে":["NAS-4575"],
"সরালে":["NAS-1269"],
"সর্বোৎকৃষ্ট":["BUK-2158","BUK-4867","BUK-6609","DAU-1047","DAU-3527","MAJ-106","MUS-221","MUS-869","MUS-1880","MUS-2701","MUS-2702","NAS-916","NAS-1433","NAS-1908","NAS-1909","NAS-2691","NAS-2703","TIR-2123","TIR-3059"],
"সরবরাহকারী":["DAU-2451","MAJ-2153","NAS-3579"],
"সরাও":["BUK-3374","NAS-762"],
"সর্বময়":["BUK-1680","DAU-884"],
"সর্বজ্ঞ":["BUK-3835","BUK-4028","BUK-4272","BUK-6520","MAJ-64","MAJ-4044","MUS-393","MUS-2128","MUS-2953","MUS-3546","MUS-6727","NAS-486","NAS-1904","NAS-2670","NAS-3179","NAS-3217","NAS-3490","TIR-242","TIR-2120","TIR-2966","TIR-3388","TIR-3507"],
"সর্দারদেরকে":["NAS-2580"],
"সর্বমোট":["NAS-1604"],
"সর্বাবস্থাই":["TIR-3599"],
"সর্বশ্রেষ্ঠ":["BUK-5","BUK-3307","BUK-3388","BUK-3405","BUK-3406","BUK-3630","BUK-3654","BUK-4343","BUK-4640","DAU-1765","DAU-1903","DAU-2098","DAU-4600","MAJ-3108","MAJ-3800","MUS-1850","MUS-3148","MUS-3562","MUS-5416","MUS-6170","TIR-479","TIR-3174"],
"সর্বাপেক্ষা":["BUK-1768","BUK-1846","BUK-2624","BUK-2993","BUK-3120","BUK-3144","BUK-3302","BUK-3393","BUK-3443","BUK-3515","BUK-3577","BUK-4076","BUK-4125","BUK-6919","BUK-6959","BUK-7015","DAU-1298","DAU-1460","MAJ-45","MAJ-154","MAJ-170","MAJ-213","MAJ-256","MAJ-3931","MAJ-3966","MAJ-3980","MAJ-4023","MAJ-4117","MAJ-4259","MUS-159","MUS-160","MUS-324","MUS-410","MUS-1403","MUS-1406","MUS-1409","MUS-1471","MUS-1758","MUS-2187","MUS-2339","MUS-2475","MUS-2879","MUS-3412","MUS-6184","MUS-6190","MUS-6191","MUS-6199","MUS-6222","MUS-6223","MUS-6224","MUS-6229","MUS-6240","MUS-6242","MUS-6243","MUS-6245","MUS-6247","MUS-6248","MUS-6269","MUS-6270","MUS-6272","MUS-6304","MUS-6360","MUS-6392","MUS-6393","MUS-6394","MUS-6444","MUS-6538","MUS-6603","MUS-6676","MUS-6677","NAS-841","NAS-4353","NAS-5362","TIR-495","TIR-714","TIR-2308","TIR-2401"],
"সর্বদার":["NAS-3473"],
"সরাসরিفرج":["DAU-242"],
"সরবরাহে":["BUK-6491"],
"সর্বনিম্নভাগের":["MUS-7146"],
"সর্বপ্রথম":["BUK-3","BUK-39","BUK-290","BUK-337","BUK-907","BUK-1452","BUK-1518","BUK-1519","BUK-1540","BUK-2306","BUK-3092","BUK-3094","BUK-3100","BUK-3112","BUK-3125","BUK-3127","BUK-3159","BUK-3169","BUK-3175","BUK-3185","BUK-3204","BUK-3318","BUK-3364","BUK-3365","BUK-3449","BUK-3487","BUK-3538","BUK-3567","BUK-3628","BUK-3629","BUK-3640","BUK-3641","BUK-3644","BUK-3654","BUK-3664","BUK-3679","BUK-3731","BUK-3752","BUK-3786","BUK-3984","BUK-3991","BUK-4032","BUK-4090","BUK-4283","BUK-4381","BUK-4385","BUK-4423","BUK-4450","BUK-4457","BUK-4499","BUK-4514","BUK-4812","BUK-5648","BUK-6009","BUK-6073","BUK-6074","BUK-6082","BUK-6085","BUK-6089","BUK-6399","BUK-6421","BUK-6627","BUK-6822","DAU-435","DAU-465","DAU-498","DAU-506","DAU-591","DAU-766","DAU-856","DAU-864","DAU-1069","DAU-1087","DAU-1173","DAU-1481","DAU-1805","DAU-1903","DAU-2418","DAU-2645","DAU-2824","DAU-2893","DAU-3143","DAU-3959","DAU-4165","MAJ-104","MAJ-150","MAJ-697","MAJ-753","MAJ-1082","MAJ-1083","MAJ-1334","MAJ-1425","MAJ-1426","MAJ-1783","MAJ-2615","MAJ-2616","MAJ-2617","MAJ-2776","MAJ-3074","MAJ-3251","MAJ-3340","MAJ-4069","MAJ-4267","MAJ-4290","MAJ-4303","MAJ-4308","MAJ-4333","MUS-1","MUS-54","MUS-83","MUS-306","MUS-371","MUS-381","MUS-483","MUS-822","MUS-825","MUS-1044","MUS-1099","MUS-1433","MUS-1435","MUS-1436","MUS-1926","MUS-1964","MUS-2028","MUS-2871","MUS-3103","MUS-3376","MUS-3608","MUS-3616","MUS-4232","MUS-4234","MUS-4527","MUS-4770","MUS-5937","MUS-5938","MUS-6090","MUS-6092","MUS-6094","MUS-6929","MUS-6937","MUS-7114","MUS-7164","NAS-96","NAS-466","NAS-467","NAS-468","NAS-1395","NAS-2734","NAS-2909","NAS-3473","NAS-3477","NAS-3503","NAS-3558","NAS-3689","NAS-3987","NAS-3993","NAS-3997","NAS-4706","NAS-5687","TIR-1205","TIR-1400","TIR-1401","TIR-2447","TIR-2611","TIR-2673","TIR-3163","TIR-3167"],
"সর্বাঙ্গ":["BUK-551","BUK-825","DAU-349","MUS-3290","MUS-7119"],
"সর্বশ্রেষ্ঠা":["BUK-3543","BUK-4974"],
"সর্বদিক":["BUK-3667"],
"সর্দারের":["BUK-3630","BUK-3689","MUS-4508","MUS-7106"],
"সর্বোতভাবে":["NAS-2817"],
"সর্বনিম্নটি":["NAS-5004"],
"সর্বজ্ঞাতা":["DAU-5000"],
"সর্ম্পকে":["BUK-4402","DAU-1664","TIR-890","TIR-929","TIR-933","TIR-960","TIR-2248"],
"সরিষার":["BUK-6053","BUK-6114","BUK-6607","BUK-7002","DAU-4047","MAJ-59","MAJ-60","MAJ-4173","MUS-85","MUS-168","MUS-375","TIR-2004"],
"সর্বশরীর":["NAS-423"],
"সর্দারকে":["BUK-1268","BUK-5338","TIR-2069"],
"সর্বদা":["BUK-478","BUK-1340","BUK-1846","BUK-2596","BUK-2896","BUK-2992","BUK-3045","BUK-3064","BUK-3091","BUK-3344","BUK-3379","BUK-3380","BUK-3584","BUK-3874","BUK-3913","BUK-4076","BUK-4086","BUK-4336","BUK-4337","BUK-4810","BUK-5031","BUK-5038","BUK-5443","BUK-5713","BUK-5775","BUK-5923","BUK-5926","BUK-5978","BUK-6058","BUK-6454","BUK-6555","BUK-6707","DAU-2476","DAU-2504","DAU-2515","DAU-2620","MAJ-7","MAJ-8","MAJ-9","MAJ-1705","MAJ-1706","MAJ-2247","MAJ-3793","MAJ-3952","MAJ-3977","MAJ-4054","MAJ-4239","MUS-201","MUS-247","MUS-250","MUS-813","MUS-824","MUS-1182","MUS-1559","MUS-1603","MUS-1803","MUS-1807","MUS-2157","MUS-2269","MUS-2498","MUS-2499","MUS-2605","MUS-2607","MUS-3957","MUS-4174","MUS-4525","MUS-4553","MUS-4800","MUS-5048","MUS-5287","MUS-6170","MUS-6294","MUS-6401","MUS-6713","MUS-6833","MUS-6894","MUS-6914","MUS-6916","MUS-6937","MUS-7012","NAS-209","NAS-796","NAS-971","NAS-1645","NAS-1655","NAS-1657","NAS-1658","NAS-1721","NAS-1724","NAS-1969","NAS-2091","NAS-2136","NAS-2176","NAS-2307","NAS-2310","NAS-2362","NAS-2363","NAS-2364","NAS-2365","NAS-2366","NAS-2380","NAS-2382","NAS-2383","NAS-2385","NAS-2386","NAS-2387","NAS-2399","NAS-2401","NAS-2403","NAS-2587","NAS-3059","NAS-3083","NAS-3085","NAS-3562","NAS-4079","NAS-4168","NAS-4639","NAS-4640","NAS-5034","NAS-5667","NAS-5673","NAS-5674","TIR-1856","TIR-1990","TIR-2529","TIR-3326"],
"সর্বত্রই":["DAU-2318"],
"সর্বযুগেই":["MUS-436"],
"সরাল":["BUK-3374","TIR-498","TIR-2251"],
"সর্বান্তকরণে":["BUK-3511","MAJ-3796","NAS-3166","TIR-1367"],
"সরবরাহের":["DAU-2722","MAJ-3066","MUS-3047","MUS-3425"],
"সর্বজ্ঞা":["NAS-1157"],
"সর্বাদিক":["BUK-3092"],
"সর্বোজ্ঞ":["MAJ-3869"],
"সরদারী":["TIR-2431"],
"সর্বোত্তমের":["TIR-3532","TIR-3608"],
"সর্বক্ষণের":["BUK-3470"],
"সর্বক্ষেত্রে":["BUK-3517"],
"সর্বস্ব":["BUK-3399"],
"সরায়":["DAU-1050","DAU-2278","MAJ-1027"],
"সরানো":["MUS-6130"],
"সর্পদংশনের":["MAJ-3519"],
"সরিয়ে":["BUK-367","BUK-423","BUK-443","BUK-457","BUK-489","BUK-622","BUK-935","BUK-960","BUK-1088","BUK-1093","BUK-1136","BUK-1172","BUK-1570","BUK-1578","BUK-1912","BUK-2182","BUK-2529","BUK-2643","BUK-2648","BUK-2733","BUK-3278","BUK-3370","BUK-3405","BUK-3413","BUK-3471","BUK-3575","BUK-3577","BUK-3616","BUK-3773","BUK-3780","BUK-3793","BUK-4098","BUK-4332","BUK-4460","BUK-4621","BUK-5139","BUK-5170","BUK-5391","BUK-5399","BUK-5549","BUK-5720","BUK-5902","BUK-5932","BUK-5937","BUK-6370","BUK-6701","DAU-713","DAU-730","DAU-734","DAU-736","DAU-900","DAU-946","DAU-1174","DAU-1591","DAU-1592","DAU-1840","DAU-2400","DAU-2756","DAU-3063","DAU-3077","DAU-3218","DAU-3457","DAU-3458","DAU-3752","DAU-3775","DAU-4026","DAU-4308","DAU-4582","DAU-4603","DAU-4718","DAU-4740","DAU-4818","DAU-5175","DAU-5176","MAJ-183","MAJ-255","MAJ-1553","MAJ-1627","MAJ-1628","MAJ-1717","MAJ-1775","MAJ-3427","MAJ-3681","MAJ-3682","MAJ-3716","MAJ-3889","MAJ-4075","MAJ-4249","MAJ-4297","MUS-360","MUS-779","MUS-837","MUS-1070","MUS-1115","MUS-1936","MUS-1956","MUS-2057","MUS-2059","MUS-2207","MUS-2806","MUS-3212","MUS-3500","MUS-3549","MUS-4481","MUS-4499","MUS-4787","MUS-5276","MUS-5342","MUS-5349","MUS-5351","MUS-5380","MUS-5436","MUS-5772","MUS-5788","MUS-5790","MUS-5949","MUS-6065","MUS-6431","MUS-6432","MUS-6435","MUS-6436","MUS-6698","MUS-7240","NAS-308","NAS-704","NAS-762","NAS-801","NAS-1600","NAS-1848","NAS-1862","NAS-2248","NAS-2251","NAS-2252","NAS-2253","NAS-2254","NAS-2255","NAS-2256","NAS-2257","NAS-2258","TIR-260","TIR-270","TIR-286","TIR-304","TIR-480","TIR-1628","TIR-1629","TIR-1756","TIR-1893","TIR-1964","TIR-2243","TIR-2374","TIR-2617","TIR-2707","TIR-2774","TIR-3136","TIR-3149","TIR-3256","TIR-3491","TIR-3522"],
"সর্দিজ্বরে":["MAJ-572"],
"সর্যগ্রহণের":["BUK-1005"],
"সর্বাপ্রথম":["MAJ-4290"],
"সর্বনিম্নের":["MUS-7148"],
"সরবপ্রথম":["DAU-2275"],
"সর্বকনিষ্ঠ":["BUK-5811","DAU-43","DAU-1379","MUS-4196","NAS-5540"],
"সর্বকনিষ্ট":["BUK-2949"],
"সরিফ":["NAS-2765"],
"সর্দার":["BUK-1195","BUK-1282","BUK-3630","BUK-3665","BUK-3835","BUK-4386","BUK-4391","BUK-4641","DAU-2988","DAU-4240","DAU-4893","MUS-376","MUS-377","MUS-3366","MUS-5545","MUS-5547","MUS-6135","MUS-6763","NAS-713","NAS-1413","NAS-3383","TIR-1061","TIR-2017","TIR-2070","TIR-2437","TIR-3313"],
"সর্বনাশা":["TIR-3186"],
"সর্বাবস্তায়":["TIR-2258"],
"সর্বাবস্থায়ই":["BUK-5822","TIR-552"],
"সর্বোচ্চ":["BUK-6918","BUK-6973"],
"সরাবে":["MUS-2202","NAS-1269","TIR-379"],
"সরদার":["BUK-2132","BUK-2261","BUK-2485","BUK-3104","BUK-3364","BUK-3368","BUK-3532","BUK-4038","BUK-4353","BUK-6624","MAJ-4308","MUS-3620","MUS-3622","MUS-5681","MUS-5736","MUS-6085","MUS-6091","MUS-6092","TIR-3148"],
"সর্বসম্মতিতে":["BUK-6688"],
"সরলভাবে":["DAU-4114"],
"সরাবার":["DAU-4470","MUS-2338"],
"সরাতে":["MUS-1685","MUS-6130"],
"সর্বাত্মক":["BUK-3471","MUS-264"],
"সর্বশেষে":["BUK-852","BUK-2751","BUK-4025","BUK-4298","BUK-4319","BUK-4402","BUK-6126","BUK-6906","BUK-6959","BUK-7003","BUK-7009","DAU-856","MUS-917","MUS-2871","MUS-3246","MUS-5862","NAS-634","TIR-3421"],
"সর্বময়":["NAS-5537"],
"সরিষা":["BUK-21","BUK-6126","BUK-7001","BUK-7002","MAJ-4053"],
"সর্বজ্ঞের":["BUK-2972"],
"সর্পে":["BUK-4209","BUK-4303"],
"সরলমান":["BUK-2485"],
"সর্বশক্তি":["BUK-3154","BUK-3454"],
"সর্বত্র":["BUK-2882","BUK-3354","BUK-4347","BUK-6370","BUK-6584","BUK-6585","DAU-1933","MAJ-1246","MAJ-3274","MAJ-4074","MAJ-4077","MAJ-4079","MUS-4732","NAS-2890","TIR-2583","TIR-2876"],
"সরলেন":["DAU-3056"],
"সর্বান্তঃকরণে":["MAJ-15","MAJ-2797","MAJ-3870"],
"সর্বশ্রেষ্ঠটি":["DAU-1683"],
"সর্বাগ্রে":["BUK-622","BUK-2751","BUK-4333","DAU-661","DAU-671","DAU-763","DAU-2536","DAU-2558","MAJ-4308","MUS-2997","MUS-4527","NAS-1065","NAS-2543","NAS-3537","NAS-3993","NAS-3994","NAS-3995","NAS-3996","NAS-3998","TIR-3421"],
"সরঞ্জামকে":["DAU-1657"],
"সরীসৃপ":["MUS-4887","NAS-4321"],
"সর্তক":["MAJ-4000","MUS-1968"],
"সর্দারদের":["MUS-2322","MUS-4403"],
"সরাচ্ছিলেন":["NAS-703","TIR-1495"],
"সর্বপেক্ষা":["MUS-2187","TIR-1"],
"সরদারদের":["BUK-5774"],
"সরিয়েছিলেন":["BUK-364"],
"সরকার":["DAU-2079"],
"সর্বাস্থায়":["TIR-1713"],
"সর্বস্বান্ত":["DAU-1640"],
"সর্বশ্রোতা":["BUK-5942","BUK-6883","DAU-5000"],
"সর্বোপরি":["BUK-1310","MUS-3608","MUS-6763","MUS-7016"],
"সরাচ্ছিলাম":["BUK-5972"],
"সর্বাবস্থায়":["BUK-299","BUK-3892","BUK-6707","DAU-4949","DAU-4974","MAJ-251","MAJ-302","MAJ-3803","MAJ-3804","MAJ-3833","NAS-267","TIR-552","TIR-2741","TIR-3560"],
"সর্বাংগে":["DAU-242","DAU-245"],
"সরাইখানা":["MAJ-242"],
"সরঞ্জামের":["MAJ-2758"],
"সর্বক্ষণ":["BUK-606","BUK-6698","DAU-275","DAU-276","MAJ-4070","MAJ-4209","MUS-207","NAS-1511","NAS-1845"],
"সরল":["BUK-38","BUK-2578","BUK-3162","BUK-3947","BUK-4347","BUK-4386","BUK-4413","DAU-4177","DAU-4535","MAJ-11","MAJ-1357","MAJ-3784","MAJ-4231","MUS-764","MUS-1684","MUS-3616","MUS-3617","MUS-6159","MUS-6663","NAS-3113","NAS-5375","TIR-1970","TIR-2490","TIR-2906","TIR-3038"],
"সরবরাহ":["BUK-2646","BUK-4021","BUK-4798","BUK-6004","BUK-6732","DAU-1320","DAU-1903","DAU-2501","MAJ-1615","MUS-4718","MUS-4847","MUS-5625"],
"সরিরে":["BUK-5534","DAU-454"],
"সর্বনাশ":["BUK-1583","BUK-1836","BUK-2306","BUK-2547","BUK-3435","BUK-3744","BUK-3745","BUK-3801","BUK-5718","BUK-5730","BUK-6724","BUK-6931","DAU-4651","DAU-4898","MAJ-2014","MAJ-3013","MUS-267","MUS-1509","MUS-1510","MUS-2323","MUS-2800","MUS-3562","MUS-3576","MUS-3905","MUS-4563","MUS-5142","MUS-5189","MUS-5193","MUS-7119","NAS-2442","NAS-4258","NAS-4727"],
"সর্ববষিয়ে":["BUK-2875"],
"সর্বমোট":["BUK-3325","BUK-3733","BUK-4835","DAU-1342","DAU-2978","MAJ-3074","MUS-1226","MUS-3637","NAS-1604"],
"সরদারের":["BUK-5828"],
"সরঞ্জাম":["BUK-2676","BUK-2692","BUK-6732","DAU-1818","DAU-2501","DAU-2771","DAU-3097","MAJ-2759","MAJ-2762"],
"সর্বনাম":["BUK-4457"],
"সর্বনিম্ন":["BUK-3603","BUK-4600","BUK-5775","DAU-886","DAU-2886","DAU-4603","MAJ-3572","MAJ-4130","MAJ-4339","MUS-60","MUS-350","MUS-362","MUS-7147","NAS-4952","TIR-261","TIR-1449","TIR-2555","TIR-2564","TIR-2615","TIR-3298","TIR-3601"],
"সর্বসাকুল্যে":["MUS-2821"],
"সরঞ্জামাদি":["BUK-3883","BUK-3884"],
"সর্বগ্রাসী":["BUK-3345","DAU-4198"],
"সরূপ":["MUS-6265"],
"সরঞ্জমাদি":["MUS-2149"],
"সর্বোত্তম":["BUK-662","BUK-1395","BUK-1429","BUK-1430","BUK-1852","BUK-2157","BUK-2591","BUK-2593","BUK-3039","BUK-3068","BUK-3094","BUK-3116","BUK-3135","BUK-3144","BUK-3191","BUK-3247","BUK-3297","BUK-3305","BUK-3307","BUK-3334","BUK-3344","BUK-3389","BUK-3395","BUK-3450","BUK-3451","BUK-3488","BUK-3518","BUK-3519","BUK-3520","BUK-3654","BUK-3702","BUK-3821","BUK-3848","BUK-4639","BUK-4657","BUK-4658","BUK-5603","BUK-5985","BUK-6203","BUK-6238","BUK-6282","BUK-6370","BUK-6726","BUK-6781","BUK-6918","DAU-354","DAU-426","DAU-543","DAU-672","DAU-678","DAU-2475","DAU-4603","DAU-4698","MAJ-45","MAJ-46","MAJ-152","MAJ-154","MAJ-176","MAJ-211","MAJ-243","MAJ-277","MAJ-278","MAJ-279","MAJ-1054","MAJ-1085","MAJ-1636","MAJ-1975","MAJ-2137","MAJ-2287","MAJ-2295","MAJ-2789","MAJ-2924","MAJ-3622","MAJ-3667","MAJ-3679","MAJ-3684","MAJ-3848","MAJ-3859","MAJ-3861","MAJ-3977","MAJ-4216","MAJ-4217","MAJ-4287","MUS-67","MUS-68","MUS-70","MUS-151","MUS-152","MUS-154","MUS-158","MUS-376","MUS-1685","MUS-1849","MUS-1878","MUS-2182","MUS-2183","MUS-2600","MUS-2613","MUS-2626","MUS-2627","MUS-4651","MUS-4658","MUS-4727","MUS-4733","MUS-4736","MUS-5437","MUS-6193","MUS-6197","MUS-6198","MUS-6226","MUS-6228","MUS-6239","MUS-6282","MUS-6283","MUS-6284","MUS-6658","MUS-7014","MUS-7017","MUS-7213","NAS-681","NAS-1376","NAS-1616","NAS-1617","NAS-1633","NAS-1663","NAS-1899","NAS-2226","NAS-2391","NAS-2394","NAS-2395","NAS-2396","NAS-2405","NAS-2528","NAS-2544","NAS-2545","NAS-2546","NAS-2626","NAS-3133","NAS-3161","NAS-3164","NAS-3235","NAS-3926","NAS-4166","NAS-4210","NAS-4450","NAS-5034","NAS-5077","NAS-5080","NAS-5435","TIR-224","TIR-450","TIR-768","TIR-991","TIR-992","TIR-994","TIR-1281","TIR-1321","TIR-1523","TIR-1561","TIR-1658","TIR-1666","TIR-1702","TIR-1759","TIR-1906","TIR-1972","TIR-2021","TIR-2168","TIR-2180","TIR-2194","TIR-2224","TIR-2269","TIR-2300","TIR-2305","TIR-2306","TIR-2332","TIR-2437","TIR-2506","TIR-2532","TIR-2901","TIR-2908","TIR-2909","TIR-3058","TIR-3094","TIR-3102","TIR-3174","TIR-3377","TIR-3383","TIR-3421","TIR-3512","TIR-3532","TIR-3571","TIR-3585","TIR-3607","TIR-3608"],
"সর্ম্পক":["BUK-2547"],
"সর্দির":["DAU-4950","MUS-6809","MUS-6810","TIR-3254"],
"সর্ববিধ":["MUS-4770"],
"সর্বশরীরে":["BUK-3113"],
"সর্বাধিকাদৃশ্য":["BUK-3490"],
"সরাসরই":["TIR-1051"],
"সর্বশ্রোতা":["BUK-4028","MAJ-3869","MUS-6616","NAS-3179","TIR-242","TIR-3388","TIR-3507"],
"সরলটি":["BUK-3308"],
"সর্বস্তরের":["BUK-1310","BUK-2948","BUK-3665"],
"সরদারকে":["BUK-2132"],
"সরষ্টা":["DAU-2167"],
"সর্বাবস্থায়":["NAS-4150","NAS-4152","NAS-4153","NAS-4154","NAS-4155","NAS-4156"],
"সরকারই":["DAU-2079"],
"সর্বাবস্থার":["NAS-3724"],
"সর্বনিকৃষ্ট":["BUK-3594","MUS-869","NAS-2571"],
"সর্ববিষয়ে":["NAS-2964"],
"সর্দারগণ":["NAS-2580"],
"সর্বশক্তিমান":["BUK-1680","BUK-2875","BUK-3063","BUK-3740","BUK-3816","BUK-4210","BUK-4967","BUK-5891","BUK-5943","BUK-5956","BUK-5961","MAJ-2235","MAJ-3878","MUS-229","MUS-3148","MUS-3558","MUS-6653","MUS-6659","MUS-6660","MUS-6661","NAS-2964"],
"সর্বোচ্চ":["BUK-587","BUK-2598","BUK-2614","BUK-2825","BUK-3405","BUK-4340","BUK-4600","BUK-6066","BUK-6619","DAU-2509","MAJ-57","MUS-60","MUS-361","NAS-2571","NAS-3349","NAS-3639","TIR-1999","TIR-2328","TIR-2532","TIR-2533","TIR-2615","TIR-2617","TIR-3116","TIR-3174","TIR-3233"],
"সর্বপ্রকার":["BUK-3625","BUK-4153","BUK-4600","BUK-5132","BUK-5365","BUK-6911","BUK-6990","DAU-1785","DAU-1903","MAJ-4034","MAJ-4083","MAJ-4166","NAS-2771","NAS-3141","NAS-5293"],
"সর্বদ্রষ্টা":["BUK-5942","BUK-6883","TIR-3507"],
"সরারি":["NAS-1124"],
"সরলা":["NAS-3672","TIR-3180"],
"সরিষাদানা":["MUS-353"],
"সরানোর":["DAU-714","MUS-6130"],
"সর্বোৎকৃষ্ট":["BUK-2456","DAU-1458","MUS-869","MUS-2700"],
"সর্বাঙ্গে":["BUK-82","DAU-246","DAU-251","MUS-637","MUS-643","NAS-247","NAS-248"],
"সরালেন":["MAJ-1624","MUS-6130"],
"সর্ববিষয়":["MAJ-4044"],
"সর্বকালের":["BUK-2341","DAU-1903","DAU-4409","MAJ-95","MAJ-3074","MUS-2814","MUS-2821"],
"সর্ববিষয়ে":["BUK-1680","BUK-2787","BUK-4272","BUK-4381","MAJ-64","MAJ-2728","MAJ-3867","MUS-229","NAS-2041"],
"সরলমনা":["BUK-6393","MUS-164"],
"সর্বক্ষণই":["NAS-2039"],
"সর্বোত্তম":["BUK-2433","BUK-2435","BUK-2475","BUK-2476","BUK-4917","BUK-7026","MUS-2627","MUS-2709","MUS-4652","MUS-4734","MUS-7110","MUS-7247"],
"সরদারদেরকে":["BUK-6926"],
"সরিয়ে":["NAS-2667","NAS-5353"],
"সর্প":["BUK-5325","MUS-5547","NAS-2456","NAS-5531","NAS-5532"],
"সর্বত্তম":["NAS-2390"],
"সর্ব":["BUK-734","BUK-3172","BUK-3435","BUK-3536","BUK-3740","BUK-4210","BUK-4270","BUK-5073","BUK-5147","BUK-5162","BUK-5811","BUK-6067","BUK-6126","BUK-6370","BUK-6560","BUK-6877","BUK-6964","DAU-8","DAU-51","DAU-313","DAU-1518","DAU-1649","DAU-4230","DAU-4259","DAU-4285","DAU-4391","DAU-4559","DAU-4583","DAU-4622","DAU-4627","DAU-4877","DAU-4991","DAU-4993","DAU-5025","DAU-5123","MAJ-3055","MAJ-3074","MUS-483","MUS-609","MUS-1045","MUS-2340","MUS-2821","MUS-3115","MUS-3204","MUS-4195","MUS-4541","MUS-5038","MUS-6111","MUS-6502","MUS-6778","MUS-6937","MUS-7240","NAS-1175","TIR-413","TIR-2158","TIR-3421"],
"সরানো":["BUK-2456","DAU-5152","MUS-1102","MUS-1103","NAS-754","NAS-4606","TIR-1124"],
"সরে":["BUK-157","BUK-225","BUK-247","BUK-255","BUK-257","BUK-263","BUK-264","BUK-271","BUK-273","BUK-277","BUK-279","BUK-281","BUK-364","BUK-370","BUK-460","BUK-484","BUK-487","BUK-631","BUK-646","BUK-653","BUK-677","BUK-678","BUK-928","BUK-962","BUK-965","BUK-994","BUK-1139","BUK-1145","BUK-1162","BUK-1282","BUK-1542","BUK-2128","BUK-2182","BUK-2219","BUK-2306","BUK-2483","BUK-2648","BUK-2873","BUK-2979","BUK-3125","BUK-3224","BUK-3268","BUK-3308","BUK-3329","BUK-3438","BUK-3581","BUK-3688","BUK-3808","BUK-4001","BUK-4031","BUK-4309","BUK-4437","BUK-4536","BUK-4537","BUK-4539","BUK-4540","BUK-4812","BUK-5452","BUK-5696","BUK-5710","BUK-6037","BUK-6136","BUK-6367","BUK-6455","BUK-6576","BUK-6658","BUK-6669","BUK-6700","BUK-6785","BUK-6799","DAU-23","DAU-152","DAU-185","DAU-245","DAU-499","DAU-634","DAU-673","DAU-940","DAU-1006","DAU-1080","DAU-1119","DAU-1127","DAU-1133","DAU-1174","DAU-1178","DAU-1236","DAU-1237","DAU-1833","DAU-2042","DAU-2161","DAU-2266","DAU-2561","DAU-2564","DAU-2643","DAU-3070","DAU-3279","DAU-3519","DAU-4683","DAU-5096","MAJ-530","MAJ-573","MAJ-1046","MAJ-1052","MAJ-1232","MAJ-1235","MAJ-1236","MAJ-1260","MAJ-1269","MAJ-1416","MAJ-1427","MAJ-1428","MAJ-1645","MAJ-1901","MAJ-1973","MAJ-1980","MAJ-2622","MAJ-2862","MAJ-3179","MAJ-3859","MAJ-4077","MUS-147","MUS-517","MUS-518","MUS-824","MUS-826","MUS-828","MUS-829","MUS-834","MUS-924","MUS-925","MUS-1026","MUS-1027","MUS-1435","MUS-1806","MUS-1820","MUS-1951","MUS-1952","MUS-1953","MUS-1974","MUS-2010","MUS-2179","MUS-2873","MUS-3366","MUS-3371","MUS-3565","MUS-4464","MUS-4468","MUS-4514","MUS-4637","MUS-4638","MUS-4807","MUS-5185","MUS-5189","MUS-5193","MUS-5772","MUS-6011","MUS-6069","MUS-6263","MUS-6693","MUS-6767","MUS-6808","MUS-7061","NAS-18","NAS-82","NAS-254","NAS-268","NAS-270","NAS-284","NAS-371","NAS-418","NAS-419","NAS-560","NAS-625","NAS-740","NAS-785","NAS-794","NAS-836","NAS-1218","NAS-1481","NAS-1507","NAS-1537","NAS-1547","NAS-1550","NAS-1834","NAS-1970","NAS-2039","NAS-2192","NAS-2571","NAS-2580","NAS-3086","NAS-3240","NAS-4347","NAS-5412","TIR-13","TIR-103","TIR-121","TIR-683","TIR-905","TIR-1757","TIR-1978","TIR-2708","TIR-2773","TIR-2859","TIR-3036","TIR-3097","TIR-3164","TIR-3232","TIR-3262","TIR-3312","TIR-3313","TIR-3600"],
"সর্বদানী":["TIR-3507"],
"সরু":["BUK-1496","BUK-1501","BUK-5507","BUK-5514","BUK-5524","MAJ-3545","MUS-2969","MUS-3616","MUS-6064","NAS-3474","NAS-3475"],
"সরী":["NAS-1039"],
"সরবাহ":["DAU-2505"],
"সর্বধিক":["BUK-6190","MAJ-2682"],
"সর্দি":["DAU-4953","MUS-7219","TIR-2743"],
"সর্বদাই":["BUK-71","BUK-3252","BUK-4453","BUK-6082","BUK-6141","BUK-6206","BUK-6229","BUK-6371","BUK-6655","BUK-6813","BUK-6951","DAU-18","DAU-1370","MAJ-2320","MUS-418","MUS-420","MUS-4209","MUS-4797","MUS-4798","MUS-4801","MUS-5153","MUS-6714","MUS-7239","NAS-1441","NAS-4071","TIR-1979"],
"সরাসরি":["BUK-3470","BUK-3489","BUK-4272","BUK-4289","DAU-693","DAU-864","DAU-1342","DAU-2845","DAU-4629","DAU-4988","MAJ-1266","MAJ-2508","MAJ-2914","MAJ-3206","MUS-228","MUS-378","MUS-386","MUS-1612","MUS-2679","MUS-2680","MUS-2684","MUS-3131","MUS-3526","MUS-3559","MUS-3562","MUS-4456","MUS-4590","MUS-4955","MUS-5053","MUS-6758","MUS-7090","NAS-1524","NAS-1604","TIR-10","TIR-2208","TIR-2726","TIR-3037","TIR-3083","TIR-3480","TIR-3518"],
"সর্দাররা":["BUK-2175","MUS-4519"],
"সর্বজন":["BUK-3371"],
"সর্বনিম্নস্তরের":["MUS-357"],
"সর্বব্যাপী":["NAS-3564"],
"সরো":["BUK-2512"],
"সরাইনি":["MAJ-2430"],
"সর":["BUK-4336"],
"সর্বসম্মত":["BUK-2831","BUK-3237","BUK-3238"],
"সরানোও":["MAJ-3683"],
"সর্বহারা":["DAU-1640"]}