{"ঈমানের":["ঈমানেরই"],
"ঈমানদারগন":["ঈমানদারগনই"],
"ঈমে":["তানঈমে","ঈমের"],
"ঈম":["তানঈমে","ঈমানদারগণের","ঈমানেরই","নুআঈম","য়াঈম","ঈমনি","ঈমান","ঈমানও","ঈমানে","ঈমানী","ঈমের","আঈম","ঈমে","ঈমা","ঈমনদারগণ","মুত্‌ঈম","তানঈম","নুয়াঈম","ঈমানদারগন","ঈমানদারগণ","ঈমানদারকে","মুতঈম","নাঈম","ঈমানদারের","ঈমানকে","নুঈম","ঈমানসহ","ঈমানের","ঈমামের","ঈমানদারদেরকে","ঈমানদারদের","ঈমানদারগনই","ঈমানদার","ঈমাদারগণ"],
"ঈমানদার":["ঈমানদারগণের","ঈমানদারগন","ঈমানদারগণ","ঈমানদারকে","ঈমানদারের","ঈমানদারদেরকে","ঈমানদারদের","ঈমানদারগনই"],
"ঈমানদারদের":["ঈমানদারদেরকে"],
"ঈমানদারগণ":["ঈমানদারগণের"],
"ঈমান":["ঈমানদারগণের","ঈমানেরই","ঈমানও","ঈমানে","ঈমানী","ঈমানদারগন","ঈমানদারগণ","ঈমানদারকে","ঈমানদারের","ঈমানকে","ঈমানসহ","ঈমানের","ঈমানদারদেরকে","ঈমানদারদের","ঈমানদারগনই","ঈমানদার"],
"ঈমানে":["ঈমানেরই","ঈমানের"],
"ঈমা":["ঈমানদারগণের","ঈমানেরই","ঈমান","ঈমানও","ঈমানে","ঈমানী","ঈমানদারগন","ঈমানদারগণ","ঈমানদারকে","ঈমানদারের","ঈমানকে","ঈমানসহ","ঈমানের","ঈমামের","ঈমানদারদেরকে","ঈমানদারদের","ঈমানদারগনই","ঈমানদার","ঈমাদারগণ"]}