{"মদ্যপ":["মদ্যপায়ীর","মদ্যপায়ীও","মদ্যপানোম্মত্ত","মদ্যপকে","মদ্যপান","মদ্যপের","মদ্যপায়ীদের","মদ্যপায়ী","মদ্যপানের","মদ্যপাত্র","মদ্যপায়ী","মদ্যপানে","মদ্যপানকালে","মদ্যপানকারী","মদ্যপায়ীকে"],
"মদ্যপায়ী":["মদ্যপায়ীর","মদ্যপায়ীও","মদ্যপায়ীদের","মদ্যপায়ীকে"],
"মদকে":["মুহাম্মদকে"],
"মদ্যপানে":["মদ্যপানের"],
"মদ্বীনা":["মদ্বীনাবাসীদের","মদ্বীনার","মদ্বীনায়","মদ্বীনাতে","মদ্বীনাবাসীর"],
"মদ্যপান":["মদ্যপানোম্মত্ত","মদ্যপানের","মদ্যপানে","মদ্যপানকালে","মদ্যপানকারী"],
"মদান":["জন্মদানকারিণী","জুমদান","আমদানীকারকের","আমদানীকারদের","হামদান","হামদানী","জন্মদান","হামদানের","জন্মদানের","আমদানি","আমদানী"],
"মদের":["গোলামদেরকে","অমুসলিমদের","মাখ্‌যূমদের","তোমদের","ইমামদের","মুসলিমদেরকে","খাদিমদের","তোমদেরকে","মুহরিমদের","আলিমদেরকে","তোমদের","নওমুসলিমদের","গোলামদের","ইয়াতীমদের","উম্মদের","খাদিমদেরও","মুসলিমদের","সক্ষমদেরকে","যুদ্ধক্ষমদের","যালেমদের","আলেমদের","হামদের","গোলামদের","খাদেমদের","আামদের","জালিমদের","তামদের","অক্ষমদের","আমদের","তোমদেরকে","তোমরামদের","উত্তমদের","মুহাম্মদের","মাহরামদের","মধ্যেমুসলিমদের","আহ্‌মদের","যালিমদের","আহমদের","আলিমদের","মযলুমদের","আমদেরকে","ইয়াতীমদের","ইয়য়াতীমদের","মুসলিমদেরই","কিরামদের","মসলিমদের"],
"মদিনাবাসী":["মদিনাবাসীর","মদিনাবাসীদের","মদিনাবাসীকে","মদিনাবাসীগণ","মদিনাবাসীগন","মদিনাবাসীরা"],
"মদদ":["মদদগার"],
"মদিনা":["মদিনা্বাসী","মদিনা্য়","মদিনায়া","মদিনায়ই","মদিনাকে","মদিনাতে","মদিনাবাসী","মদিনাকেও","মদিনাবাসীর","মদিনায়","মদিনাও","মদিনাই","মদিনার","জীবদ্দশায়আমিমদিনায়","মদিনাতেও","মদিনাতেই","মদিনাবাসীদের","মদিনাবাসিগণ","সঙ্গেমদিনাথেকে","মদিনাবাসীকে","মদিনাবাসীগণ","মদিনাবাসীগন","মদিনাবাসীরা"],
"মদীনা":["মদীনাবাসীগণের","মদীনাকে","মদীনাতে","মদীনায়","মদীনাবাসীকে","মদীনাবাসীগণ","মদীনাবাসীগন","মদীনাবাসীরা","মদীনাবাসীদের","মদীনাবাসী","মদীনাও","মদীনাই","মদীনার","মদীনায়","মদীনাতিনা"],
"মদ্":["মদ্যপায়ীর","মদ্যপায়ীও","মদ্যপানোম্মত্ত","ধর্মদ্রোহী","মদ্যপকে","মদ্যপান","মদ্যপের","কদমদ্বয়ের","ধর্মদ্রোহিতা","মদ্যপায়ীদের","মদ্বীনাবাসীদের","মদ্বীনার","মদ্বীনায়","মদ্যপায়ী","মদ্যপ","কদমদ্বয়","মদ্যপানের","মদ্যপাত্র","মদ্যপায়ী","মদ্বীনাতে","মদ্যপানে","হামদ্‌","মদ্যপানকালে","মদ্যপানকারী","মদ্বীনা","মদ্বীনয়","মদ্বীনাবাসীর","মুহাম্মদ্","মদ্য","মদ্যপায়ীকে"],
"মদীনাবাসীগণ":["মদীনাবাসীগণের"],
"মদিনায়":["মদিনায়া","মদিনায়ই","জীবদ্দশায়আমিমদিনায়"],
"মদ্য":["মদ্যপায়ীর","মদ্যপায়ীও","মদ্যপানোম্মত্ত","মদ্যপকে","মদ্যপান","মদ্যপের","মদ্যপায়ীদের","মদ্যপায়ী","মদ্যপ","মদ্যপানের","মদ্যপাত্র","মদ্যপায়ী","মদ্যপানে","মদ্যপানকালে","মদ্যপানকারী","মদ্যপায়ীকে"],
"মদপান":["মদপানের"],
"মদিনাতে":["মদিনাতেও","মদিনাতেই"],
"মদিনাবাসীর":["মদিনাবাসীরা"],
"মদ":["মুহামমদ","খামদর","মদীনাবাসীগণের","জন্মদানকারিণী","হামদুল্লিাহ","তামীমদারীর","বামদিককে","মদ্যপায়ীর","মদ্যপায়ীও","গোলামদেরকে","বামদিকের","অমুসলিমদের","মদিনা্বাসী","মদ্যপানোম্মত্ত","মাখ্‌যূমদের","মদিনা্য়","মদিনায়া","মদিনায়ই","আলহামদুলিল্লহ","তোমদের","জন্মদাতা","মদিনাকে","ইমামদের","মদিনাতে","ধর্মদ্রোহী","পয়গামদাতাদের","মদ্যপকে","মুসলিমদেরকে","মদ্যপান","জুমদান","খাদিমদের","মদ্যপের","মদীনাকে","মদীনাতে","শামদেশ","মদীনায়","কদমদ্বয়ের","তামীমদারী","আহমদে","ওয়াসাল্লামদাঁড়িয়ে","তোমদেরকে","হামদুলিল্লাহ","পরিণামদর্শিতা","অনুমদিত","মুহরিমদের","আলিমদেরকে","তোমদের","নওমুসলিমদের","ওয়াসাল্লামদুব্বা","বিহামদিহী","বিহামদিহি","গোলামদের","ইয়াতীমদের","উম্মদের","ধর্মদ্রোহিতা","খাদিমদেরও","তামিমদারি","মদ্যপায়ীদের","মদ্বীনাবাসীদের","আমদানীকারকের","দামদর","মুসলিমদের","বিহামদিকা","মদীনা","সমদামের","মদিনা","সক্ষমদেরকে","সুক্ষ্মদর্শী","মোহাম্মদ","আলহামদু","মদ্বীনার","মদ্বীনায়","যুদ্ধক্ষমদের","প্রথমদিকে","হামদুলিল্লাহ্","হামদুলিল্লাহি","মদ্যপায়ী","মদ্যপ","প্রথমদিকের","কদমদ্বয়","মুহাস্মদ","বিহামদিকাল্লাহুম্মাগফিরলী","যালেমদের","মূহাম্মদ","আমদানীকারদের","আম্মদ","আলেমদের","হামদের","হামদান","সূক্ষ্মদর্শী","মদ্যপানের","হামদহ্","শামদেশে","নবীমুহাম্মদ","মদ্যপাত্র","সুঠামদেহী","হামদিকা","হামদাযী","গোলামদের","হামদানী","পশ্চিমদিকে","মদিনাবাসী","জন্মদান","মদিনাকেও","মদিনাবাসীর","মদখোর","খাদেমদের","মদ্যপায়ী","মুহাম্মদসাল্লাল্লাহু","মদ্বীনাতে","আামদের","মুাহাম্মদ","মদীনাবাসীকে","মদীনাবাসীগণ","মদীনাবাসীগন","মদীনাবাসীরা","আহম্মদ","মুহাম্মদীকে","তোমদরেকে","হামদানের","জন্মদানের","মদ্যপানে","আলহামদুলিল্লাহ্","আলহামদুলিল্লাহি","মহাম্মদ","মদিনায়","মদিনাও","মদিনাই","মদিনার","হামদ্‌","জালিমদের","মদীনাবাসীদের","হামদ","জন্মদাতার","তামদের","অক্ষমদের","মুহামামদ","আমদেদ","আমদের","আরামদায়ক","তোমদেরকে","বামদিকে","মদপান","আহ্‌মদ","হামদও","জীবদ্দশায়আমিমদিনায়","হামদু","হামদা","মদিনাতেও","মদিনাতেই","তোমরামদের","মুহম্মদ","মদ্যপানকালে","মদ্যপানকারী","মুহামদ","উত্তমদের","মদ্বীনা","মদ্বীনয়","আলহামদুল্লিাহ","মধ্যমদেহী","ওয়াবিহামদিহি","মদমত্ত","মদ্বীনাবাসীর","তামীমদারীকে","মদীনাবাসী","যিম্মদারি","মুহাম্মদুর","মুহাম্মদীর","মুহাম্মদের","মদগুলো","মুহাম্মদএর","মুহাম্মদকে","মুহাম্মদ","মুহাম্মদাদ","মাহরামদের","আহামদ","মধ্যেমুসলিমদের","আহ্‌মদের","মদদ","মদই","মদ্","মদদগার","যালিমদের","আহমদের","আলহামদুলিল্লাহ","আলিমদের","ওয়ালহামদু","মদিনাবাসীদের","মযলুমদের","মুহাম্মামদ","আমদেরকে","ইয়াতীমদের","হাম্মদ","ইয়য়াতীমদের","পরমদয়ালু","জন্মদিনের","মদীনাও","মদীনাই","মদীনার","মদীনায়","মদিনাবাসিগণ","সঙ্গেমদিনাথেকে","মুসলিমদেরই","মদিনাবাসীকে","মদিনাবাসীগণ","মদিনাবাসীগন","বেহামদিহি","মদিনাবাসীরা","মদীনাতিনা","কিরামদের","মদতো","মুহাম্মদও","মুহাম্মদা","মুহাম্মদ্","মুহাম্মদী","মদান","মুহাম্মমদ","আমদানি","আমদানী","মদকে","রাসুলমদ","মসলিমদের","মদের","মদ্য","মদ্যপায়ীকে","আহমদ","আলহামদুলিল্লাহ্‌","মদপানের"],
"মদিনাকে":["মদিনাকেও"],
"মদীনাবাসী":["মদীনাবাসীগণের","মদীনাবাসীকে","মদীনাবাসীগণ","মদীনাবাসীগন","মদীনাবাসীরা","মদীনাবাসীদের"]}